{
  "schema": "cockpit/v2",
  "meta": {
    "generatedAt": "2026-07-09T15:32:23.828Z",
    "historyPoints": 265
  },
  "regime": "neutral",
  "moneyLocation": "偏 CEX 合约(投机/杠杆主导)",
  "layers": {
    "macro": {
      "layer": "macro",
      "direction": "neutral",
      "strength": 48.3,
      "confidence": "high",
      "components": [
        {
          "metric": "netLiquidityUsdB",
          "value": 5841,
          "changePct": -0.02
        },
        {
          "metric": "walclUsdB",
          "value": 6724.6
        },
        {
          "metric": "tgaUsdB",
          "value": 880.2
        },
        {
          "metric": "rrpUsdB",
          "value": 3.3
        }
      ],
      "rotationEdges": [],
      "drivers": [
        "净流动性走平"
      ],
      "dataQuality": "ok"
    },
    "launchpad": {
      "layer": "launchpad",
      "direction": "heating",
      "strength": 41,
      "confidence": "high",
      "components": [
        {
          "launchpad": "pumpfun",
          "label": "pump.fun",
          "chain": "solana",
          "revenue24h": 612039,
          "revenue7d": 5101538,
          "revenueAllTime": 1056755393,
          "share": 89.1,
          "momentum": -0.16,
          "direction": "cooling",
          "strength": 16,
          "dataQuality": "ok"
        },
        {
          "launchpad": "letsbonk",
          "label": "LetsBonk/BONK.fun",
          "chain": "solana",
          "revenue24h": 2273,
          "revenue7d": 56335,
          "revenueAllTime": 38621443,
          "share": 0.3,
          "momentum": -0.718,
          "direction": "flat",
          "strength": null,
          "dataQuality": "ok"
        },
        {
          "launchpad": "believe",
          "label": "Believe",
          "chain": "solana",
          "revenue24h": 0,
          "revenue7d": 10,
          "revenueAllTime": 32728624,
          "share": 0,
          "momentum": -1,
          "direction": "flat",
          "strength": null,
          "dataQuality": "ok"
        },
        {
          "launchpad": "moonshot",
          "label": "Moonshot",
          "chain": "solana",
          "revenue24h": 12469,
          "revenue7d": 61876,
          "revenueAllTime": 63920680,
          "share": 1.8,
          "momentum": 0.411,
          "direction": "heating",
          "strength": 41,
          "dataQuality": "ok"
        },
        {
          "launchpad": "fourmeme",
          "label": "four.meme",
          "chain": "bsc",
          "revenue24h": 60086,
          "revenue7d": 563078,
          "revenueAllTime": 95434031,
          "share": 8.7,
          "momentum": -0.253,
          "direction": "cooling",
          "strength": 25,
          "dataQuality": "ok"
        }
      ],
      "byChain": [
        {
          "chain": "solana",
          "revenue24h": 626781,
          "share": 91.3
        },
        {
          "chain": "bsc",
          "revenue24h": 60086,
          "share": 8.7
        }
      ],
      "topLaunchpad": {
        "launchpad": "pumpfun",
        "label": "pump.fun",
        "revenue24h": 612039,
        "share": 89.1
      },
      "totalRevenue24h": 686867,
      "rotationEdges": [],
      "drivers": [
        "Moonshot 发射台收入升温"
      ],
      "dataQuality": "ok"
    },
    "chain": {
      "layer": "chain",
      "direction": "stable",
      "strength": 39,
      "confidence": "high",
      "components": [
        {
          "chain": "solana",
          "label": "SOL",
          "shareNow": 4.8733,
          "shareDeltaPp": 0.0252,
          "direction": "inflow",
          "strength": 31,
          "inflection": null,
          "dataQuality": "ok",
          "dexVolChange1dPct": -4.23,
          "dexVol24hUsd": 2443787706,
          "dexVolChange7dPct": 4.56,
          "dexVolChange7dRawPct": null,
          "dexVolChange7dUntrusted": false,
          "dexVolChange7dNote": null,
          "feesMomentum": -0.031,
          "feeSpike": null,
          "accel6h": 0.1134,
          "accel1h": -0.4476,
          "pxMom6h": 22.325,
          "fastScore": 0.3339,
          "midScore": -0.0254,
          "slowScore": 0.824,
          "compositeScore": 0.3062,
          "flowType": "trading",
          "persistence": {
            "label": "持续(1-3d)",
            "hours": 1,
            "momentum": "building",
            "breadth": 2,
            "slowFollow": true,
            "dataQuality": "ok"
          }
        },
        {
          "chain": "base",
          "label": "Base",
          "shareNow": 1.5717,
          "shareDeltaPp": 0.0059,
          "direction": "flat",
          "strength": 0,
          "inflection": null,
          "dataQuality": "ok",
          "dexVolChange1dPct": -29.5,
          "dexVol24hUsd": 817074728,
          "dexVolChange7dPct": -6.97,
          "dexVolChange7dRawPct": null,
          "dexVolChange7dUntrusted": false,
          "dexVolChange7dNote": null,
          "feesMomentum": 0.265,
          "feeSpike": null,
          "accel6h": 0.1145,
          "accel1h": -0.0691,
          "pxMom6h": -1.001,
          "fastScore": 0.0481,
          "midScore": -0.071,
          "slowScore": 0,
          "compositeScore": -0.0032,
          "flowType": null,
          "persistence": {
            "label": "无显著流向",
            "hours": 0,
            "momentum": "flat",
            "breadth": 0,
            "slowFollow": false,
            "dataQuality": "partial"
          }
        },
        {
          "chain": "ethereum",
          "label": "ETH 主网",
          "shareNow": 49.8132,
          "shareDeltaPp": -0.2439,
          "direction": "flat",
          "strength": 3,
          "inflection": "down",
          "dataQuality": "ok",
          "dexVolChange1dPct": 63.84,
          "dexVol24hUsd": 1585477882,
          "dexVolChange7dPct": 38.35,
          "dexVolChange7dRawPct": null,
          "dexVolChange7dUntrusted": false,
          "dexVolChange7dNote": null,
          "feesMomentum": 0.258,
          "feeSpike": null,
          "accel6h": 0.0066,
          "accel1h": -0.2712,
          "pxMom6h": -0.368,
          "fastScore": -0.0086,
          "midScore": 0.4862,
          "slowScore": -0.996,
          "compositeScore": -0.0329,
          "flowType": null,
          "persistence": {
            "label": "无显著流向",
            "hours": 0,
            "momentum": "flat",
            "breadth": 0,
            "slowFollow": false,
            "dataQuality": "partial"
          }
        },
        {
          "chain": "bsc",
          "label": "BSC",
          "shareNow": 4.6891,
          "shareDeltaPp": 0.1715,
          "direction": "inflow",
          "strength": 15,
          "inflection": null,
          "dataQuality": "ok",
          "dexVolChange1dPct": 4.49,
          "dexVol24hUsd": 743195050,
          "dexVolChange7dPct": -0.53,
          "dexVolChange7dRawPct": null,
          "dexVolChange7dUntrusted": false,
          "dexVolChange7dNote": null,
          "feesMomentum": -0.236,
          "feeSpike": null,
          "accel6h": -0.0528,
          "accel1h": -0.0126,
          "pxMom6h": -3.101,
          "fastScore": -0.047,
          "midScore": -0.0675,
          "slowScore": 0.996,
          "compositeScore": 0.1544,
          "flowType": "trading",
          "persistence": {
            "label": "闪现(日内)",
            "hours": 1,
            "momentum": "building",
            "breadth": 1,
            "slowFollow": true,
            "dataQuality": "ok"
          }
        },
        {
          "chain": "robinhood",
          "label": "Robinhood",
          "shareNow": 0.0907,
          "shareDeltaPp": 0.0033,
          "direction": "inflow",
          "strength": 39,
          "inflection": null,
          "dataQuality": "ok",
          "dexVolChange1dPct": 1235.84,
          "dexVol24hUsd": 433191164,
          "dexVolChange7dPct": 1000,
          "dexVolChange7dRawPct": 79777278.27,
          "dexVolChange7dUntrusted": true,
          "dexVolChange7dNote": "新链·基数低",
          "feesMomentum": 3.501,
          "feeSpike": {
            "protocol": "Robinhood Chain",
            "share": 98,
            "discount": 0.95
          },
          "accel6h": null,
          "accel1h": null,
          "pxMom6h": null,
          "fastScore": null,
          "midScore": 0.62,
          "slowScore": 0,
          "compositeScore": 0.3945,
          "flowType": "trading",
          "persistence": {
            "label": "闪现(日内)",
            "hours": 11,
            "momentum": "fading",
            "breadth": 2,
            "slowFollow": false,
            "dataQuality": "ok"
          }
        }
      ],
      "rotationEdges": [],
      "drivers": [
        "多链无显著资金轮动"
      ],
      "dataQuality": "ok"
    },
    "narrative": {
      "layer": "narrative",
      "eps7dPct": 2,
      "direction": "flat",
      "strength": 100,
      "confidence": "high",
      "components": [
        {
          "sector": "CEX",
          "tvl": 240861195181,
          "change7dPct": 1.3,
          "change1dPct": 0.76,
          "direction": "flat",
          "strength": 12.5,
          "protocolCount": 77,
          "topProtocols": [
            {
              "name": "Binance CEX",
              "tvl": 135653996990,
              "change7dPct": 0.98,
              "change1dPct": 0.5
            },
            {
              "name": "OKX",
              "tvl": 21777278085,
              "change7dPct": 0.72,
              "change1dPct": 0.26
            },
            {
              "name": "Bitfinex",
              "tvl": 16364454541,
              "change7dPct": 3.06,
              "change1dPct": 0.46
            }
          ],
          "dataQuality": "ok"
        },
        {
          "sector": "Bridge",
          "tvl": 45426387024,
          "change7dPct": 2.24,
          "change1dPct": 0.28,
          "direction": "rotate_in",
          "strength": 25,
          "protocolCount": 145,
          "topProtocols": [
            {
              "name": "LayerZero V2",
              "tvl": 7218214944,
              "change7dPct": -1.19,
              "change1dPct": -1.69
            },
            {
              "name": "WBTC",
              "tvl": 7141417233,
              "change7dPct": 2.3,
              "change1dPct": 0.88
            },
            {
              "name": "Coinbase Bridge",
              "tvl": 5768174849,
              "change7dPct": 4.17,
              "change1dPct": 1.42
            }
          ],
          "dataQuality": "ok"
        },
        {
          "sector": "Lending",
          "tvl": 37807597794,
          "change7dPct": 2.31,
          "change1dPct": -0.13,
          "direction": "rotate_in",
          "strength": 37.5,
          "protocolCount": 565,
          "topProtocols": [
            {
              "name": "Aave V3",
              "tvl": 12273177223,
              "change7dPct": 1.6,
              "change1dPct": -1.31
            },
            {
              "name": "Morpho Blue",
              "tvl": 6991814335,
              "change7dPct": 3.7,
              "change1dPct": 0.01
            },
            {
              "name": "SparkLend",
              "tvl": 3554637714,
              "change7dPct": 2.04,
              "change1dPct": 0.34
            }
          ],
          "dataQuality": "ok"
        },
        {
          "sector": "Liquid Staking",
          "tvl": 33387146764,
          "change7dPct": 3.86,
          "change1dPct": 0.43,
          "direction": "rotate_in",
          "strength": 50,
          "protocolCount": 253,
          "topProtocols": [
            {
              "name": "Lido",
              "tvl": 15991471725,
              "change7dPct": 6.26,
              "change1dPct": 0.57
            },
            {
              "name": "Binance staked ETH",
              "tvl": 6454847731,
              "change7dPct": 4.46,
              "change1dPct": -0.14
            },
            {
              "name": "Sanctum Validator LSTs",
              "tvl": 1124691684,
              "change7dPct": -3.63,
              "change1dPct": 0.52
            }
          ],
          "dataQuality": "ok"
        },
        {
          "sector": "RWA",
          "tvl": 24267253241,
          "change7dPct": 1447407.35,
          "change1dPct": 0.18,
          "direction": "rotate_in",
          "strength": 87.5,
          "protocolCount": 121,
          "topProtocols": [
            {
              "name": "Circle USYC",
              "tvl": 3108104504,
              "change7dPct": 0.04,
              "change1dPct": 0.02
            },
            {
              "name": "BlackRock BUIDL",
              "tvl": 3053924336,
              "change7dPct": 0.21,
              "change1dPct": 0.01
            },
            {
              "name": "Tether Gold",
              "tvl": 2924372761,
              "change7dPct": 0.91,
              "change1dPct": 0.81
            }
          ],
          "dataQuality": "ok"
        },
        {
          "sector": "Dexs",
          "tvl": 11582119576,
          "change7dPct": 111271399,
          "change1dPct": 0.66,
          "direction": "rotate_in",
          "strength": 100,
          "protocolCount": 1748,
          "topProtocols": [
            {
              "name": "PancakeSwap AMM",
              "tvl": 1665184217,
              "change7dPct": -0.18,
              "change1dPct": 0.56
            },
            {
              "name": "Uniswap V3",
              "tvl": 1450701223,
              "change7dPct": 3.67,
              "change1dPct": 0.65
            },
            {
              "name": "Curve DEX",
              "tvl": 1265120449,
              "change7dPct": 1.72,
              "change1dPct": 1.3
            }
          ],
          "dataQuality": "ok"
        },
        {
          "sector": "Staking Pool",
          "tvl": 9615417213,
          "change7dPct": 4.38,
          "change1dPct": -0.72,
          "direction": "rotate_in",
          "strength": 62.5,
          "protocolCount": 35,
          "topProtocols": [
            {
              "name": "SSV Network",
              "tvl": 8504625766,
              "change7dPct": 5.21,
              "change1dPct": -0.8
            },
            {
              "name": "Obol",
              "tvl": 548658239,
              "change7dPct": -6.63,
              "change1dPct": -2.34
            },
            {
              "name": "Marinade Native",
              "tvl": 222793332,
              "change7dPct": 5.94,
              "change1dPct": 3.92
            }
          ],
          "dataQuality": "ok"
        },
        {
          "sector": "CDP",
          "tvl": 8255284451,
          "change7dPct": 6.6,
          "change1dPct": -1.21,
          "direction": "rotate_in",
          "strength": 75,
          "protocolCount": 194,
          "topProtocols": [
            {
              "name": "Sky Lending",
              "tvl": 5838221678,
              "change7dPct": 9.5,
              "change1dPct": -1.04
            },
            {
              "name": "USDD",
              "tvl": 1292432079,
              "change7dPct": -1.6,
              "change1dPct": -3.2
            },
            {
              "name": "Lista CDP",
              "tvl": 308872396,
              "change7dPct": 0.89,
              "change1dPct": 1.28
            }
          ],
          "dataQuality": "ok"
        }
      ],
      "rotationEdges": [],
      "drivers": [
        "Dexs 板块资金轮入"
      ],
      "mindshare": {
        "trendingCoins": [
          {
            "symbol": "CASHCAT",
            "name": "Cash Cat",
            "marketCapRank": 271,
            "change24hPct": 18
          },
          {
            "symbol": "LAB",
            "name": "LAB",
            "marketCapRank": 135,
            "change24hPct": -31
          },
          {
            "symbol": "ANSEM",
            "name": "The Black Bull",
            "marketCapRank": 217,
            "change24hPct": 7
          },
          {
            "symbol": "ARB",
            "name": "Arbitrum",
            "marketCapRank": 97,
            "change24hPct": 14
          },
          {
            "symbol": "SLX",
            "name": "Solstice",
            "marketCapRank": 525,
            "change24hPct": -16
          },
          {
            "symbol": "PENGU",
            "name": "Pudgy Penguins",
            "marketCapRank": 115,
            "change24hPct": 2
          },
          {
            "symbol": "SENT",
            "name": "Sentient",
            "marketCapRank": 239,
            "change24hPct": 18
          },
          {
            "symbol": "HYPE",
            "name": "Hyperliquid",
            "marketCapRank": 10,
            "change24hPct": 2
          },
          {
            "symbol": "VVV",
            "name": "Venice Token",
            "marketCapRank": 98,
            "change24hPct": 9
          },
          {
            "symbol": "PI",
            "name": "Pi Network",
            "marketCapRank": 64,
            "change24hPct": -4
          }
        ],
        "trendingCategories": [
          {
            "name": "Derivatives"
          },
          {
            "name": "Perpetuals"
          },
          {
            "name": "Rollup"
          },
          {
            "name": "Privacy Infrastructure"
          },
          {
            "name": "Decentralized Exchange (DEX)"
          },
          {
            "name": "Mobile Mining"
          }
        ],
        "source": "coingecko-trending",
        "note": "热门搜索/注意力代理,可被刷量操纵,不代表真实资金流"
      },
      "dataQuality": "ok"
    },
    "dexCex": {
      "layer": "dexCex",
      "direction": "to_perp",
      "strength": 4,
      "confidence": "high",
      "crowding": "normal",
      "perpSpotRatio": 7.59,
      "components": [
        {
          "symbol": "BTC",
          "funding": 0.0000340673350566,
          "perpSpot": 4.42
        },
        {
          "symbol": "ETH",
          "funding": 0.0000368169410015,
          "perpSpot": 26.27
        },
        {
          "symbol": "SOL",
          "funding": 0.0000303890083265,
          "perpSpot": 14.49
        },
        {
          "symbol": "BNB",
          "funding": 0.0000663854088665,
          "perpSpot": 7.43
        }
      ],
      "rotationEdges": [],
      "drivers": [
        "资金偏合约"
      ],
      "dataQuality": "ok"
    }
  },
  "flowState": {
    "regime": "neutral",
    "moneyLocation": "偏 CEX 合约(投机/杠杆主导)",
    "rotationEdges": [],
    "agreement": {
      "bullish": 1,
      "bearish": 1,
      "net": "mixed"
    },
    "confidence": "high"
  },
  "guidance": [
    {
      "target": "ANSEM",
      "type": "onchain_spot",
      "conviction": 19,
      "tier": "flat",
      "tierLabel": "空仓",
      "tailwindLayers": [
        {
          "layer": "chain",
          "reason": "SOL 链上资金净流入",
          "pts": 0.093
        }
      ],
      "headwindLayers": [
        {
          "layer": "链活动热度",
          "reason": "SOL 协议收入动量降温",
          "pts": 0.002
        },
        {
          "layer": "dexCex",
          "reason": "资金偏向 CEX 合约,现货承接弱",
          "pts": 0.008
        }
      ],
      "riskFlags": [],
      "rationale": "仓位档:空仓 · 顺风:chain · 逆风:链活动热度/dexCex",
      "chainTag": "solana",
      "metrics": {
        "priceUsd": 0.319266533400819,
        "px5mPct": -0.194,
        "px1hPct": 0.638,
        "px6hPct": 6.029,
        "px24hPct": 8.993,
        "vol6hUsd": 5331230.60633699,
        "vol24hUsd": 17426115.8585686,
        "liqUsd": 2851269.0991,
        "buys24h": 15065,
        "sells24h": 14994,
        "fdvUsd": 317722112.930585,
        "marketCapUsd": 132070939.870581,
        "ca": "9cRCn9rGT8V2imeM2BaKs13yhMEais3ruM3rPvTGpump",
        "source": "geckoterminal",
        "at": "2026-07-09T15:32:25.228Z"
      },
      "factors": [
        {
          "key": "layers",
          "label": "五层信号",
          "score": 5,
          "pts": 5,
          "detail": "层信号 rawT=0.093、rawH=0.01，宏观系数 1，按 60% 计入。"
        },
        {
          "key": "momentum",
          "label": "标的动量",
          "score": 0.311,
          "pts": 6.2,
          "detail": "标的动量按可用周期重归一计算，px24hPct=+8.99%、px6hPct=+6.03%、px1hPct=+0.64%，合成 +6.43%。"
        },
        {
          "key": "flow",
          "label": "买卖失衡",
          "score": 0.005,
          "pts": 0,
          "detail": "24h 买卖笔数 15065/14994，失衡度 +0.002。"
        },
        {
          "key": "turnover",
          "label": "成交/流动性",
          "score": 0.786,
          "pts": 7.9,
          "detail": "24h 成交额 17426116 美元、流动性 2851269 美元，换手 6.11x。"
        }
      ],
      "dataQuality": "ok"
    },
    {
      "target": "CUPSEY",
      "type": "onchain_spot",
      "conviction": 30,
      "tier": "probe",
      "tierLabel": "试探",
      "tailwindLayers": [
        {
          "layer": "chain",
          "reason": "SOL 链上资金净流入",
          "pts": 0.093
        }
      ],
      "headwindLayers": [
        {
          "layer": "链活动热度",
          "reason": "SOL 协议收入动量降温",
          "pts": 0.002
        },
        {
          "layer": "launchpad",
          "reason": "pump.fun 发射台降温",
          "pts": 0.048
        },
        {
          "layer": "dexCex",
          "reason": "资金偏向 CEX 合约,现货承接弱",
          "pts": 0.008
        }
      ],
      "riskFlags": [],
      "rationale": "仓位档:试探 · 顺风:chain · 逆风:链活动热度/launchpad/dexCex",
      "chainTag": "solana",
      "metrics": {
        "priceUsd": 0.009953567285445756,
        "px5mPct": -0.229,
        "px1hPct": 3.201,
        "px6hPct": 39.458,
        "px24hPct": 28.059,
        "vol6hUsd": 969026.246552581,
        "vol24hUsd": 5543911.83674524,
        "liqUsd": 325578.6255,
        "buys24h": 20663,
        "sells24h": 20187,
        "fdvUsd": 9942294.09203378,
        "marketCapUsd": 9938111.64862967,
        "ca": "6NwarBvDkXhByqVp2Qkq5i9XbtA2B3Bwe8SWGu9vpump",
        "source": "geckoterminal",
        "at": "2026-07-09T15:32:25.228Z"
      },
      "factors": [
        {
          "key": "layers",
          "label": "五层信号",
          "score": 2.1,
          "pts": 2.1,
          "detail": "层信号 rawT=0.093、rawH=0.058，宏观系数 1，按 60% 计入。"
        },
        {
          "key": "momentum",
          "label": "标的动量",
          "score": 0.868,
          "pts": 17.4,
          "detail": "标的动量按可用周期重归一计算，px24hPct=+28.06%、px6hPct=+39.46%、px1hPct=+3.2%，合成 +26.51%。"
        },
        {
          "key": "flow",
          "label": "买卖失衡",
          "score": 0.023,
          "pts": 0.2,
          "detail": "24h 买卖笔数 20663/20187，失衡度 +0.012。"
        },
        {
          "key": "turnover",
          "label": "成交/流动性",
          "score": 1,
          "pts": 10,
          "detail": "24h 成交额 5543912 美元、流动性 325579 美元，换手 17.03x。"
        }
      ],
      "dataQuality": "ok"
    },
    {
      "target": "HOOD",
      "type": "onchain_spot",
      "conviction": 40,
      "tier": "flat",
      "tierLabel": "空仓",
      "tailwindLayers": [
        {
          "layer": "chain",
          "reason": "SOL 链上资金净流入",
          "pts": 0.093
        }
      ],
      "headwindLayers": [
        {
          "layer": "链活动热度",
          "reason": "SOL 协议收入动量降温",
          "pts": 0.002
        },
        {
          "layer": "dexCex",
          "reason": "资金偏向 CEX 合约,现货承接弱",
          "pts": 0.008
        }
      ],
      "riskFlags": [
        "流动性薄(<$30万)，出场滑点风险"
      ],
      "rationale": "仓位档:空仓 · 顺风:chain · 逆风:链活动热度/dexCex · 风险:1 项",
      "chainTag": "solana",
      "metrics": {
        "priceUsd": 0.000018245161751965665,
        "px5mPct": 0.621,
        "px1hPct": -12.252,
        "px6hPct": -22.316,
        "px24hPct": 161.651,
        "vol6hUsd": 230682.014117103,
        "vol24hUsd": 1786750.62454253,
        "liqUsd": 201630.7534,
        "buys24h": 10236,
        "sells24h": 5995,
        "fdvUsd": 815546.195671618,
        "marketCapUsd": 816491.083742986,
        "ca": "h5NciPdMZ5QCB5BYETJMYBMpVx9ZuitR6HcVjyBhood",
        "source": "geckoterminal",
        "at": "2026-07-09T15:32:25.228Z"
      },
      "factors": [
        {
          "key": "layers",
          "label": "五层信号",
          "score": 5,
          "pts": 5,
          "detail": "层信号 rawT=0.093、rawH=0.01，宏观系数 1，按 60% 计入。"
        },
        {
          "key": "momentum",
          "label": "标的动量",
          "score": 0.998,
          "pts": 20,
          "detail": "标的动量按可用周期重归一计算，px24hPct=+161.65%、px6hPct=-22.32%、px1hPct=-12.25%，合成 +71.68%。"
        },
        {
          "key": "flow",
          "label": "买卖失衡",
          "score": 0.523,
          "pts": 5.2,
          "detail": "24h 买卖笔数 10236/5995，失衡度 +0.261。"
        },
        {
          "key": "turnover",
          "label": "成交/流动性",
          "score": 0.948,
          "pts": 9.5,
          "detail": "24h 成交额 1786751 美元、流动性 201631 美元，换手 8.86x。"
        }
      ],
      "dataQuality": "ok"
    },
    {
      "target": "VVV",
      "type": "onchain_spot",
      "conviction": 10,
      "tier": "flat",
      "tierLabel": "空仓",
      "tailwindLayers": [
        {
          "layer": "链活动热度",
          "reason": "Base 协议收入动量升温",
          "pts": 0.013
        }
      ],
      "headwindLayers": [
        {
          "layer": "dexCex",
          "reason": "资金偏向 CEX 合约,现货承接弱",
          "pts": 0.008
        }
      ],
      "riskFlags": [],
      "rationale": "仓位档:空仓 · 顺风:链活动热度 · 逆风:dexCex",
      "chainTag": "base",
      "metrics": {
        "priceUsd": 11.4743337060907,
        "px5mPct": -0.644,
        "px1hPct": -1.78,
        "px6hPct": 0.283,
        "px24hPct": 8.983,
        "vol6hUsd": 239828.090916601,
        "vol24hUsd": 1014521.10400591,
        "liqUsd": 7818112.2476,
        "buys24h": 3313,
        "sells24h": 1880,
        "fdvUsd": 924488239.514587,
        "marketCapUsd": 542081126.702741,
        "ca": "0xacfe6019ed1a7dc6f7b508c02d1b04ec88cc21bf",
        "source": "geckoterminal",
        "at": "2026-07-09T15:32:25.228Z"
      },
      "factors": [
        {
          "key": "layers",
          "label": "五层信号",
          "score": 0.3,
          "pts": 0.3,
          "detail": "层信号 rawT=0.013、rawH=0.008，宏观系数 1，按 60% 计入。"
        },
        {
          "key": "momentum",
          "label": "标的动量",
          "score": 0.208,
          "pts": 4.2,
          "detail": "标的动量按可用周期重归一计算，px24hPct=+8.98%、px6hPct=+0.28%、px1hPct=-1.78%，合成 +4.22%。"
        },
        {
          "key": "flow",
          "label": "买卖失衡",
          "score": 0.552,
          "pts": 5.5,
          "detail": "24h 买卖笔数 3313/1880，失衡度 +0.276。"
        },
        {
          "key": "turnover",
          "label": "成交/流动性",
          "score": 0,
          "pts": 0,
          "detail": "24h 成交额 1014521 美元、流动性 7818112 美元，换手 0.13x。"
        }
      ],
      "dataQuality": "ok"
    },
    {
      "target": "AERO",
      "type": "onchain_spot",
      "conviction": 4,
      "tier": "flat",
      "tierLabel": "空仓",
      "tailwindLayers": [
        {
          "layer": "链活动热度",
          "reason": "Base 协议收入动量升温",
          "pts": 0.013
        }
      ],
      "headwindLayers": [
        {
          "layer": "dexCex",
          "reason": "资金偏向 CEX 合约,现货承接弱",
          "pts": 0.008
        }
      ],
      "riskFlags": [],
      "rationale": "仓位档:空仓 · 顺风:链活动热度 · 逆风:dexCex",
      "chainTag": "base",
      "metrics": {
        "priceUsd": 0.526564420223744,
        "px5mPct": -0.22,
        "px1hPct": -0.415,
        "px6hPct": -2.348,
        "px24hPct": 0.873,
        "vol6hUsd": 1280853.67630109,
        "vol24hUsd": 4843395.78665908,
        "liqUsd": 988771.6311,
        "buys24h": 1584,
        "sells24h": 2048,
        "fdvUsd": 1019291990.39812,
        "marketCapUsd": 508058380.031097,
        "ca": "0x940181a94a35a4569e4529a3cdfb74e38fd98631",
        "source": "geckoterminal",
        "at": "2026-07-09T15:32:25.228Z"
      },
      "factors": [
        {
          "key": "layers",
          "label": "五层信号",
          "score": 0.3,
          "pts": 0.3,
          "detail": "层信号 rawT=0.013、rawH=0.008，宏观系数 1，按 60% 计入。"
        },
        {
          "key": "momentum",
          "label": "标的动量",
          "score": -0.018,
          "pts": -0.4,
          "detail": "标的动量按可用周期重归一计算，px24hPct=+0.87%、px6hPct=-2.35%、px1hPct=-0.41%，合成 -0.35%。"
        },
        {
          "key": "flow",
          "label": "买卖失衡",
          "score": -0.256,
          "pts": -2.6,
          "detail": "24h 买卖笔数 1584/2048，失衡度 -0.128。"
        },
        {
          "key": "turnover",
          "label": "成交/流动性",
          "score": 0.69,
          "pts": 6.9,
          "detail": "24h 成交额 4843396 美元、流动性 988772 美元，换手 4.9x。"
        }
      ],
      "dataQuality": "ok"
    },
    {
      "target": "VIRTUAL",
      "type": "onchain_spot",
      "conviction": 11,
      "tier": "flat",
      "tierLabel": "空仓",
      "tailwindLayers": [
        {
          "layer": "链活动热度",
          "reason": "Base 协议收入动量升温",
          "pts": 0.013
        }
      ],
      "headwindLayers": [
        {
          "layer": "dexCex",
          "reason": "资金偏向 CEX 合约,现货承接弱",
          "pts": 0.008
        }
      ],
      "riskFlags": [],
      "rationale": "仓位档:空仓 · 顺风:链活动热度 · 逆风:dexCex",
      "chainTag": "base",
      "metrics": {
        "priceUsd": 0.527964564176864,
        "px5mPct": -0.028,
        "px1hPct": 0.634,
        "px6hPct": 0.5,
        "px24hPct": 1.788,
        "vol6hUsd": 900380.617377106,
        "vol24hUsd": 3409935.39118538,
        "liqUsd": 322491.008,
        "buys24h": 5061,
        "sells24h": 5331,
        "fdvUsd": 262333129.496215,
        "marketCapUsd": 347100712.753632,
        "ca": "0x0b3e328455c4059eeb9e3f84b5543f74e24e7e1b",
        "source": "geckoterminal",
        "at": "2026-07-09T15:32:25.228Z"
      },
      "factors": [
        {
          "key": "layers",
          "label": "五层信号",
          "score": 0.3,
          "pts": 0.3,
          "detail": "层信号 rawT=0.013、rawH=0.008，宏观系数 1，按 60% 计入。"
        },
        {
          "key": "momentum",
          "label": "标的动量",
          "score": 0.058,
          "pts": 1.2,
          "detail": "标的动量按可用周期重归一计算，px24hPct=+1.79%、px6hPct=+0.5%、px1hPct=+0.63%，合成 +1.17%。"
        },
        {
          "key": "flow",
          "label": "买卖失衡",
          "score": -0.052,
          "pts": -0.5,
          "detail": "24h 买卖笔数 5061/5331，失衡度 -0.026。"
        },
        {
          "key": "turnover",
          "label": "成交/流动性",
          "score": 1,
          "pts": 10,
          "detail": "24h 成交额 3409935 美元、流动性 322491 美元，换手 10.57x。"
        }
      ],
      "dataQuality": "ok"
    },
    {
      "target": "ASTEROID",
      "type": "onchain_spot",
      "conviction": 0,
      "tier": "flat",
      "tierLabel": "空仓",
      "tailwindLayers": [
        {
          "layer": "链活动热度",
          "reason": "ETH 主网 协议收入动量升温",
          "pts": 0.014
        }
      ],
      "headwindLayers": [
        {
          "layer": "dexCex",
          "reason": "资金偏向 CEX 合约,现货承接弱",
          "pts": 0.008
        }
      ],
      "riskFlags": [],
      "rationale": "仓位档:空仓 · 顺风:链活动热度 · 逆风:dexCex",
      "chainTag": "ethereum",
      "metrics": {
        "priceUsd": 0.0000574229282739958,
        "px5mPct": 0.483,
        "px1hPct": 1.139,
        "px6hPct": -0.008,
        "px24hPct": -1.712,
        "vol6hUsd": 131445.16855698,
        "vol24hUsd": 1100554.96833472,
        "liqUsd": 1609973.9754,
        "buys24h": 663,
        "sells24h": 821,
        "fdvUsd": 24156598.3134473,
        "marketCapUsd": 24157251.6939063,
        "ca": "0xf280b16ef293d8e534e370794ef26bf312694126",
        "source": "geckoterminal",
        "at": "2026-07-09T15:32:25.228Z"
      },
      "factors": [
        {
          "key": "layers",
          "label": "五层信号",
          "score": 0.4,
          "pts": 0.4,
          "detail": "层信号 rawT=0.014、rawH=0.008，宏观系数 1，按 60% 计入。"
        },
        {
          "key": "momentum",
          "label": "标的动量",
          "score": -0.032,
          "pts": -0.6,
          "detail": "标的动量按可用周期重归一计算，px24hPct=-1.71%、px6hPct=-0.01%、px1hPct=+1.14%，合成 -0.63%。"
        },
        {
          "key": "flow",
          "label": "买卖失衡",
          "score": -0.213,
          "pts": -2.1,
          "detail": "24h 买卖笔数 663/821，失衡度 -0.106。"
        },
        {
          "key": "turnover",
          "label": "成交/流动性",
          "score": 0,
          "pts": 0,
          "detail": "24h 成交额 1100555 美元、流动性 1609974 美元，换手 0.68x。"
        }
      ],
      "dataQuality": "ok"
    },
    {
      "target": "UNI",
      "type": "onchain_spot",
      "conviction": 1,
      "tier": "flat",
      "tierLabel": "空仓",
      "tailwindLayers": [
        {
          "layer": "链活动热度",
          "reason": "ETH 主网 协议收入动量升温",
          "pts": 0.014
        }
      ],
      "headwindLayers": [
        {
          "layer": "dexCex",
          "reason": "资金偏向 CEX 合约,现货承接弱",
          "pts": 0.008
        }
      ],
      "riskFlags": [],
      "rationale": "仓位档:空仓 · 顺风:链活动热度 · 逆风:dexCex",
      "chainTag": "ethereum",
      "metrics": {
        "priceUsd": 3.3279414717206,
        "px5mPct": -0.124,
        "px1hPct": 0.45,
        "px6hPct": -0.241,
        "px24hPct": 0.989,
        "vol6hUsd": 973501.002785365,
        "vol24hUsd": 4634079.12052627,
        "liqUsd": 13559503.9623,
        "buys24h": 327,
        "sells24h": 338,
        "fdvUsd": 2972285764.46449,
        "marketCapUsd": 2066663506.56855,
        "ca": "0x1f9840a85d5af5bf1d1762f925bdaddc4201f984",
        "source": "geckoterminal",
        "at": "2026-07-09T15:32:25.228Z"
      },
      "factors": [
        {
          "key": "layers",
          "label": "五层信号",
          "score": 0.4,
          "pts": 0.4,
          "detail": "层信号 rawT=0.014、rawH=0.008，宏观系数 1，按 60% 计入。"
        },
        {
          "key": "momentum",
          "label": "标的动量",
          "score": 0.026,
          "pts": 0.5,
          "detail": "标的动量按可用周期重归一计算，px24hPct=+0.99%、px6hPct=-0.24%、px1hPct=+0.45%，合成 +0.51%。"
        },
        {
          "key": "flow",
          "label": "买卖失衡",
          "score": -0.033,
          "pts": -0.3,
          "detail": "24h 买卖笔数 327/338，失衡度 -0.017。"
        },
        {
          "key": "turnover",
          "label": "成交/流动性",
          "score": 0,
          "pts": 0,
          "detail": "24h 成交额 4634079 美元、流动性 13559504 美元，换手 0.34x。"
        }
      ],
      "dataQuality": "ok"
    },
    {
      "target": "VANRY",
      "type": "onchain_spot",
      "conviction": 11,
      "tier": "flat",
      "tierLabel": "空仓",
      "tailwindLayers": [
        {
          "layer": "链活动热度",
          "reason": "ETH 主网 协议收入动量升温",
          "pts": 0.014
        }
      ],
      "headwindLayers": [
        {
          "layer": "dexCex",
          "reason": "资金偏向 CEX 合约,现货承接弱",
          "pts": 0.008
        }
      ],
      "riskFlags": [],
      "rationale": "仓位档:空仓 · 顺风:链活动热度 · 逆风:dexCex",
      "chainTag": "ethereum",
      "metrics": {
        "priceUsd": 0.00766938464585445,
        "px5mPct": -0.161,
        "px1hPct": -2.665,
        "px6hPct": 2.339,
        "px24hPct": 18.466,
        "vol6hUsd": 195169.185683339,
        "vol24hUsd": 746717.090007383,
        "liqUsd": 514618.7899,
        "buys24h": 1297,
        "sells24h": 1315,
        "fdvUsd": 17918104.4864492,
        "marketCapUsd": 16490868.8474835,
        "ca": "0x8de5b80a0c1b02fe4976851d030b36122dbb8624",
        "source": "geckoterminal",
        "at": "2026-07-09T15:32:25.228Z"
      },
      "factors": [
        {
          "key": "layers",
          "label": "五层信号",
          "score": 0.4,
          "pts": 0.4,
          "detail": "层信号 rawT=0.014、rawH=0.008，宏观系数 1，按 60% 计入。"
        },
        {
          "key": "momentum",
          "label": "标的动量",
          "score": 0.438,
          "pts": 8.8,
          "detail": "标的动量按可用周期重归一计算，px24hPct=+18.47%、px6hPct=+2.34%、px1hPct=-2.66%，合成 +9.4%。"
        },
        {
          "key": "flow",
          "label": "买卖失衡",
          "score": -0.014,
          "pts": -0.1,
          "detail": "24h 买卖笔数 1297/1315，失衡度 -0.007。"
        },
        {
          "key": "turnover",
          "label": "成交/流动性",
          "score": 0.162,
          "pts": 1.6,
          "detail": "24h 成交额 746717 美元、流动性 514619 美元，换手 1.45x。"
        }
      ],
      "dataQuality": "ok"
    },
    {
      "target": "LAB",
      "type": "onchain_spot",
      "conviction": 0,
      "tier": "flat",
      "tierLabel": "空仓",
      "tailwindLayers": [
        {
          "layer": "chain",
          "reason": "BSC 链上资金净流入",
          "pts": 0.045
        }
      ],
      "headwindLayers": [
        {
          "layer": "链活动热度",
          "reason": "BSC 协议收入动量降温",
          "pts": 0.013
        },
        {
          "layer": "dexCex",
          "reason": "资金偏向 CEX 合约,现货承接弱",
          "pts": 0.008
        }
      ],
      "riskFlags": [],
      "rationale": "仓位档:空仓 · 顺风:chain · 逆风:链活动热度/dexCex",
      "chainTag": "bsc",
      "metrics": {
        "priceUsd": 0.876972812877489,
        "px5mPct": -0.06,
        "px1hPct": -2.868,
        "px6hPct": -4.64,
        "px24hPct": -34.979,
        "vol6hUsd": 36832297.1119486,
        "vol24hUsd": 177752242.208319,
        "liqUsd": 2830231.5991,
        "buys24h": 155017,
        "sells24h": 174544,
        "fdvUsd": 877134198.395857,
        "marketCapUsd": 274142018.691865,
        "ca": "0x7ec43cf65f1663f820427c62a5780b8f2e25593a",
        "source": "geckoterminal",
        "at": "2026-07-09T15:32:25.228Z"
      },
      "factors": [
        {
          "key": "layers",
          "label": "五层信号",
          "score": 1.4,
          "pts": 1.4,
          "detail": "层信号 rawT=0.045、rawH=0.021，宏观系数 1，按 60% 计入。"
        },
        {
          "key": "momentum",
          "label": "标的动量",
          "score": -0.75,
          "pts": -15,
          "detail": "标的动量按可用周期重归一计算，px24hPct=-34.98%、px6hPct=-4.64%、px1hPct=-2.87%，合成 -19.46%。"
        },
        {
          "key": "flow",
          "label": "买卖失衡",
          "score": -0.119,
          "pts": -1.2,
          "detail": "24h 买卖笔数 155017/174544，失衡度 -0.059。"
        },
        {
          "key": "turnover",
          "label": "成交/流动性",
          "score": 1,
          "pts": 10,
          "detail": "24h 成交额 177752242 美元、流动性 2830232 美元，换手 62.8x。"
        }
      ],
      "dataQuality": "ok"
    },
    {
      "target": "TCC",
      "type": "onchain_spot",
      "conviction": 18,
      "tier": "flat",
      "tierLabel": "空仓",
      "tailwindLayers": [
        {
          "layer": "chain",
          "reason": "BSC 链上资金净流入",
          "pts": 0.045
        }
      ],
      "headwindLayers": [
        {
          "layer": "链活动热度",
          "reason": "BSC 协议收入动量降温",
          "pts": 0.013
        },
        {
          "layer": "dexCex",
          "reason": "资金偏向 CEX 合约,现货承接弱",
          "pts": 0.008
        }
      ],
      "riskFlags": [],
      "rationale": "仓位档:空仓 · 顺风:chain · 逆风:链活动热度/dexCex",
      "chainTag": "bsc",
      "metrics": {
        "priceUsd": 0.00607652706595436,
        "px5mPct": 1.579,
        "px1hPct": -13.564,
        "px6hPct": 3.299,
        "px24hPct": 11.487,
        "vol6hUsd": 471916.95699934,
        "vol24hUsd": 6532039.83703856,
        "liqUsd": 307046.1562,
        "buys24h": 17189,
        "sells24h": 13772,
        "fdvUsd": 6076960.059,
        "marketCapUsd": null,
        "ca": "0xa4390b901a63641c92327e5793b45fcb46954444",
        "source": "geckoterminal",
        "at": "2026-07-09T15:32:25.228Z"
      },
      "factors": [
        {
          "key": "layers",
          "label": "五层信号",
          "score": 1.4,
          "pts": 1.4,
          "detail": "层信号 rawT=0.045、rawH=0.021，宏观系数 1，按 60% 计入。"
        },
        {
          "key": "momentum",
          "label": "标的动量",
          "score": 0.198,
          "pts": 4,
          "detail": "标的动量按可用周期重归一计算，px24hPct=+11.49%、px6hPct=+3.3%、px1hPct=-13.56%，合成 +4.02%。"
        },
        {
          "key": "flow",
          "label": "买卖失衡",
          "score": 0.221,
          "pts": 2.2,
          "detail": "24h 买卖笔数 17189/13772，失衡度 +0.11。"
        },
        {
          "key": "turnover",
          "label": "成交/流动性",
          "score": 1,
          "pts": 10,
          "detail": "24h 成交额 6532040 美元、流动性 307046 美元，换手 21.27x。"
        }
      ],
      "dataQuality": "ok"
    },
    {
      "target": "POWER",
      "type": "onchain_spot",
      "conviction": 0,
      "tier": "flat",
      "tierLabel": "空仓",
      "tailwindLayers": [
        {
          "layer": "chain",
          "reason": "BSC 链上资金净流入",
          "pts": 0.045
        }
      ],
      "headwindLayers": [
        {
          "layer": "链活动热度",
          "reason": "BSC 协议收入动量降温",
          "pts": 0.013
        },
        {
          "layer": "dexCex",
          "reason": "资金偏向 CEX 合约,现货承接弱",
          "pts": 0.008
        }
      ],
      "riskFlags": [],
      "rationale": "仓位档:空仓 · 顺风:chain · 逆风:链活动热度/dexCex",
      "chainTag": "bsc",
      "metrics": {
        "priceUsd": 0.0776074376106324,
        "px5mPct": -0.724,
        "px1hPct": -10.4,
        "px6hPct": -18.084,
        "px24hPct": -17.393,
        "vol6hUsd": 1210861.85821735,
        "vol24hUsd": 10874293.8621265,
        "liqUsd": 420984.794,
        "buys24h": 59295,
        "sells24h": 61962,
        "fdvUsd": 3409532.30457507,
        "marketCapUsd": 16287464.3631,
        "ca": "0x9dc44ae5be187eca9e2a67e33f27a4c91cea1223",
        "source": "geckoterminal",
        "at": "2026-07-09T15:32:25.228Z"
      },
      "factors": [
        {
          "key": "layers",
          "label": "五层信号",
          "score": 1.4,
          "pts": 1.4,
          "detail": "层信号 rawT=0.045、rawH=0.021，宏观系数 1，按 60% 计入。"
        },
        {
          "key": "momentum",
          "label": "标的动量",
          "score": -0.67,
          "pts": -13.4,
          "detail": "标的动量按可用周期重归一计算，px24hPct=-17.39%、px6hPct=-18.08%、px1hPct=-10.4%，合成 -16.2%。"
        },
        {
          "key": "flow",
          "label": "买卖失衡",
          "score": -0.044,
          "pts": -0.4,
          "detail": "24h 买卖笔数 59295/61962，失衡度 -0.022。"
        },
        {
          "key": "turnover",
          "label": "成交/流动性",
          "score": 1,
          "pts": 10,
          "detail": "24h 成交额 10874294 美元、流动性 420985 美元，换手 25.83x。"
        }
      ],
      "dataQuality": "ok"
    }
  ],
  "appRevenueHeat": {
    "layer": "appRevenue",
    "dataQuality": "ok",
    "note": "协议收入=活动热度,非流动性/净流入",
    "byChain": [
      {
        "chain": "solana",
        "label": "SOL",
        "dataQuality": "ok",
        "totalRevenue24h": 3149609,
        "topApps": [
          {
            "protocol": "pump.fun",
            "revenue24h": 612039,
            "revenue7d": 5101538,
            "share": 19.4,
            "momentum": -0.16,
            "direction": "cooling"
          },
          {
            "protocol": "Collector Crypt",
            "revenue24h": 419979,
            "revenue7d": 2088111,
            "share": 13.3,
            "momentum": 0.408,
            "direction": "heating"
          },
          {
            "protocol": "PumpSwap",
            "revenue24h": 271585,
            "revenue7d": 2235367,
            "share": 8.6,
            "momentum": -0.15,
            "direction": "cooling"
          },
          {
            "protocol": "Phantom Wallet",
            "revenue24h": 226372,
            "revenue7d": 1860696,
            "share": 7.2,
            "momentum": -0.148,
            "direction": "cooling"
          },
          {
            "protocol": "Axiom",
            "revenue24h": 185551,
            "revenue7d": 1801213,
            "share": 5.9,
            "momentum": -0.279,
            "direction": "cooling"
          }
        ],
        "chainHeat": true,
        "dominantApp": {
          "protocol": "pump.fun",
          "revenue24h": 612039,
          "share": 19.4
        },
        "singleAppSpike": false
      },
      {
        "chain": "base",
        "label": "Base",
        "dataQuality": "ok",
        "totalRevenue24h": 608323,
        "topApps": [
          {
            "protocol": "Aerodrome Slipstream",
            "revenue24h": 162633,
            "revenue7d": 863441,
            "share": 26.7,
            "momentum": 0.318,
            "direction": "heating"
          },
          {
            "protocol": "Base",
            "revenue24h": 93954,
            "revenue7d": 469402,
            "share": 15.4,
            "momentum": 0.401,
            "direction": "heating"
          },
          {
            "protocol": "SoSoValue Indexes",
            "revenue24h": 54617,
            "revenue7d": 359516,
            "share": 9,
            "momentum": 0.063,
            "direction": "heating"
          },
          {
            "protocol": "Aerodrome V1",
            "revenue24h": 44041,
            "revenue7d": 227495,
            "share": 7.2,
            "momentum": 0.355,
            "direction": "heating"
          },
          {
            "protocol": "Uniswap V3",
            "revenue24h": 39808,
            "revenue7d": 308004,
            "share": 6.5,
            "momentum": -0.095,
            "direction": "cooling"
          }
        ],
        "chainHeat": true,
        "dominantApp": {
          "protocol": "Aerodrome Slipstream",
          "revenue24h": 162633,
          "share": 26.7
        },
        "singleAppSpike": false
      },
      {
        "chain": "ethereum",
        "label": "ETH 主网",
        "dataQuality": "ok",
        "totalRevenue24h": 1565658,
        "topApps": [
          {
            "protocol": "Sky Lending",
            "revenue24h": 454161,
            "revenue7d": 3106253,
            "share": 29,
            "momentum": 0.023,
            "direction": "flat"
          },
          {
            "protocol": "Curve DEX",
            "revenue24h": 131908,
            "revenue7d": 319797,
            "share": 8.4,
            "momentum": 1.887,
            "direction": "heating"
          },
          {
            "protocol": "Aave V3",
            "revenue24h": 95732,
            "revenue7d": 634131,
            "share": 6.1,
            "momentum": 0.057,
            "direction": "heating"
          },
          {
            "protocol": "Lido",
            "revenue24h": 68233,
            "revenue7d": 474697,
            "share": 4.4,
            "momentum": 0.006,
            "direction": "flat"
          },
          {
            "protocol": "Titan Builder",
            "revenue24h": 68050,
            "revenue7d": 2368659,
            "share": 4.3,
            "momentum": -0.799,
            "direction": "cooling"
          }
        ],
        "chainHeat": true,
        "dominantApp": {
          "protocol": "Sky Lending",
          "revenue24h": 454161,
          "share": 29
        },
        "singleAppSpike": false
      },
      {
        "chain": "bsc",
        "label": "BSC",
        "dataQuality": "ok",
        "totalRevenue24h": 493413,
        "topApps": [
          {
            "protocol": "GMGN",
            "revenue24h": 163126,
            "revenue7d": 1714159,
            "share": 33.1,
            "momentum": -0.334,
            "direction": "cooling"
          },
          {
            "protocol": "four.meme",
            "revenue24h": 60086,
            "revenue7d": 563078,
            "share": 12.2,
            "momentum": -0.253,
            "direction": "cooling"
          },
          {
            "protocol": "Binance Alpha",
            "revenue24h": 39543,
            "revenue7d": 400004,
            "share": 8,
            "momentum": -0.308,
            "direction": "cooling"
          },
          {
            "protocol": "BSC",
            "revenue24h": 36482,
            "revenue7d": 236206,
            "share": 7.4,
            "momentum": 0.081,
            "direction": "heating"
          },
          {
            "protocol": "PancakeSwap AMM V3",
            "revenue24h": 34201,
            "revenue7d": 237516,
            "share": 6.9,
            "momentum": 0.008,
            "direction": "flat"
          }
        ],
        "chainHeat": true,
        "dominantApp": {
          "protocol": "GMGN",
          "revenue24h": 163126,
          "share": 33.1
        },
        "singleAppSpike": false
      },
      {
        "chain": "robinhood",
        "label": "Robinhood",
        "dataQuality": "ok",
        "totalRevenue24h": 35154,
        "topApps": [
          {
            "protocol": "Robinhood Chain",
            "revenue24h": 34532,
            "revenue7d": 53169,
            "share": 98.2,
            "momentum": 3.546,
            "direction": "heating"
          },
          {
            "protocol": "Rialto Aggregator",
            "revenue24h": 612,
            "revenue7d": 2222,
            "share": 1.7,
            "momentum": 0.928,
            "direction": "heating"
          },
          {
            "protocol": "Prynt",
            "revenue24h": 10,
            "revenue7d": 10,
            "share": 0,
            "momentum": 6,
            "direction": "flat"
          },
          {
            "protocol": "Curve DEX",
            "revenue24h": 0,
            "revenue7d": 0,
            "share": 0,
            "momentum": null,
            "direction": "unknown"
          },
          {
            "protocol": "PancakeSwap AMM",
            "revenue24h": 0,
            "revenue7d": 0,
            "share": 0,
            "momentum": null,
            "direction": "unknown"
          }
        ],
        "chainHeat": true,
        "dominantApp": {
          "protocol": "Robinhood Chain",
          "revenue24h": 34532,
          "share": 98.2
        },
        "singleAppSpike": true
      }
    ]
  },
  "stableTide": {
    "sideChannel": "stableTide",
    "mcapUsd": 303207030628,
    "spanHours": 159.8,
    "points": 85,
    "note": "总量=钱进出 crypto 池子的变化;链间份额=池内轮动。旁路展示,不进五层引擎/conviction(v1)。",
    "direction": "flat",
    "delta24hPct": 0.004,
    "delta7dPct": null,
    "emaGapPct": null,
    "cusumAlarm": null,
    "dataQuality": "partial"
  },
  "dataHealth": {
    "layers": [
      {
        "layer": "macro",
        "dataQuality": "ok",
        "confidence": "high"
      },
      {
        "layer": "launchpad",
        "dataQuality": "ok",
        "confidence": "high"
      },
      {
        "layer": "chain",
        "dataQuality": "ok",
        "confidence": "high"
      },
      {
        "layer": "narrative",
        "dataQuality": "ok",
        "confidence": "high"
      },
      {
        "layer": "dexCex",
        "dataQuality": "ok",
        "confidence": "high"
      }
    ],
    "sourceStatus": [
      {
        "source": "fred-net-liquidity",
        "status": "ok"
      },
      {
        "source": "defillama-stablecoinchains",
        "status": "ok"
      },
      {
        "source": "geckoterminal-trending",
        "status": "partial",
        "message": "robinhood: unsupported GeckoTerminal chain robinhood; fallback unsupported CoinGecko category robinhood"
      },
      {
        "source": "defillama-launchpad-fees",
        "status": "ok"
      },
      {
        "source": "defillama-chain-fees",
        "status": "ok"
      },
      {
        "source": "defillama-dexs",
        "status": "ok"
      },
      {
        "source": "coingecko-trending",
        "status": "ok"
      },
      {
        "source": "defillama-categories",
        "status": "ok"
      },
      {
        "source": "okx-derivatives",
        "status": "ok"
      }
    ]
  },
  "advisory": "本面板为资金流向辅助判断,仅供观察与仓位参考,不构成下单指令;真实交易由用户手动执行。"
}
