{
  "schema": "cockpit/v2",
  "meta": {
    "generatedAt": "2026-07-08T16:48:35.601Z",
    "historyPoints": 257
  },
  "regime": "neutral",
  "moneyLocation": "偏 CEX 合约(投机/杠杆主导)",
  "layers": {
    "macro": {
      "layer": "macro",
      "direction": "neutral",
      "strength": 54.8,
      "confidence": "high",
      "components": [
        {
          "metric": "netLiquidityUsdB",
          "value": 5839.8,
          "changePct": -0.06
        },
        {
          "metric": "walclUsdB",
          "value": 6724.6
        },
        {
          "metric": "tgaUsdB",
          "value": 880.2
        },
        {
          "metric": "rrpUsdB",
          "value": 4.5
        }
      ],
      "rotationEdges": [],
      "drivers": [
        "净流动性走平"
      ],
      "dataQuality": "ok"
    },
    "launchpad": {
      "layer": "launchpad",
      "direction": "heating",
      "strength": 64,
      "confidence": "high",
      "components": [
        {
          "launchpad": "pumpfun",
          "label": "pump.fun",
          "chain": "solana",
          "revenue24h": 799202,
          "revenue7d": 5287471,
          "revenueAllTime": 1056143354,
          "share": 85.2,
          "momentum": 0.058,
          "direction": "heating",
          "strength": 6,
          "dataQuality": "ok"
        },
        {
          "launchpad": "letsbonk",
          "label": "LetsBonk/BONK.fun",
          "chain": "solana",
          "revenue24h": 3686,
          "revenue7d": 73054,
          "revenueAllTime": 38621257,
          "share": 0.4,
          "momentum": -0.647,
          "direction": "flat",
          "strength": null,
          "dataQuality": "ok"
        },
        {
          "launchpad": "believe",
          "label": "Believe",
          "chain": "solana",
          "revenue24h": 1,
          "revenue7d": 10,
          "revenueAllTime": 32728624,
          "share": 0,
          "momentum": -0.3,
          "direction": "flat",
          "strength": null,
          "dataQuality": "ok"
        },
        {
          "launchpad": "moonshot",
          "label": "Moonshot",
          "chain": "solana",
          "revenue24h": 7449,
          "revenue7d": 52587,
          "revenueAllTime": 63908211,
          "share": 0.8,
          "momentum": -0.008,
          "direction": "flat",
          "strength": null,
          "dataQuality": "ok"
        },
        {
          "launchpad": "fourmeme",
          "label": "four.meme",
          "chain": "bsc",
          "revenue24h": 127446,
          "revenue7d": 543592,
          "revenueAllTime": 95373945,
          "share": 13.6,
          "momentum": 0.641,
          "direction": "heating",
          "strength": 64,
          "dataQuality": "ok"
        }
      ],
      "byChain": [
        {
          "chain": "solana",
          "revenue24h": 810338,
          "share": 86.4
        },
        {
          "chain": "bsc",
          "revenue24h": 127446,
          "share": 13.6
        }
      ],
      "topLaunchpad": {
        "launchpad": "pumpfun",
        "label": "pump.fun",
        "revenue24h": 799202,
        "share": 85.2
      },
      "totalRevenue24h": 937784,
      "rotationEdges": [],
      "drivers": [
        "four.meme 发射台收入升温"
      ],
      "dataQuality": "ok"
    },
    "chain": {
      "layer": "chain",
      "direction": "stable",
      "strength": 69,
      "confidence": "medium",
      "components": [
        {
          "chain": "solana",
          "label": "SOL",
          "shareNow": 4.9203,
          "shareDeltaPp": -0.006,
          "direction": "inflow",
          "strength": 7,
          "inflection": null,
          "dataQuality": "ok",
          "dexVolChange1dPct": 19.75,
          "dexVol24hUsd": 2563314275,
          "dexVolChange7dPct": 9.31,
          "dexVolChange7dRawPct": null,
          "dexVolChange7dUntrusted": false,
          "dexVolChange7dNote": null,
          "feesMomentum": 0.199,
          "feeSpike": null,
          "accel6h": -0.2806,
          "accel1h": 0.298,
          "pxMom6h": 10.768,
          "fastScore": 0.0069,
          "midScore": 0.1981,
          "slowScore": 0,
          "compositeScore": 0.0724,
          "flowType": "trading",
          "persistence": {
            "label": "闪现(日内)",
            "hours": 1,
            "momentum": "fading",
            "breadth": 3,
            "slowFollow": false,
            "dataQuality": "ok"
          }
        },
        {
          "chain": "base",
          "label": "Base",
          "shareNow": 1.58,
          "shareDeltaPp": 0.0065,
          "direction": "inflow",
          "strength": 18,
          "inflection": null,
          "dataQuality": "ok",
          "dexVolChange1dPct": 61.16,
          "dexVol24hUsd": 1151091174,
          "dexVolChange7dPct": 43.8,
          "dexVolChange7dRawPct": null,
          "dexVolChange7dUntrusted": false,
          "dexVolChange7dNote": null,
          "feesMomentum": 0.182,
          "feeSpike": null,
          "accel6h": 0.115,
          "accel1h": 0.0413,
          "pxMom6h": -0.042,
          "fastScore": 0.0671,
          "midScore": 0.4398,
          "slowScore": 0,
          "compositeScore": 0.1841,
          "flowType": "trading",
          "persistence": {
            "label": "持续(1-3d)",
            "hours": 4,
            "momentum": "building",
            "breadth": 4,
            "slowFollow": false,
            "dataQuality": "ok"
          }
        },
        {
          "chain": "ethereum",
          "label": "ETH 主网",
          "shareNow": 50.2008,
          "shareDeltaPp": 0.1202,
          "direction": "inflow",
          "strength": 34,
          "inflection": "down",
          "dataQuality": "ok",
          "dexVolChange1dPct": -15.26,
          "dexVol24hUsd": 967886928,
          "dexVolChange7dPct": 4.55,
          "dexVolChange7dRawPct": null,
          "dexVolChange7dUntrusted": false,
          "dexVolChange7dNote": null,
          "feesMomentum": 4.376,
          "feeSpike": null,
          "accel6h": 0.1349,
          "accel1h": -0.4123,
          "pxMom6h": 0.003,
          "fastScore": 0.0784,
          "midScore": 0.3084,
          "slowScore": 0.968,
          "compositeScore": 0.3368,
          "flowType": "trading",
          "persistence": {
            "label": "持续(1-3d)",
            "hours": 1,
            "momentum": "building",
            "breadth": 2,
            "slowFollow": true,
            "dataQuality": "ok"
          }
        },
        {
          "chain": "bsc",
          "label": "BSC",
          "shareNow": 4.5352,
          "shareDeltaPp": -0.1623,
          "direction": "flat",
          "strength": 3,
          "inflection": null,
          "dataQuality": "ok",
          "dexVolChange1dPct": 79,
          "dexVol24hUsd": 714850941,
          "dexVolChange7dPct": 0.8,
          "dexVolChange7dRawPct": null,
          "dexVolChange7dUntrusted": false,
          "dexVolChange7dNote": null,
          "feesMomentum": 0.344,
          "feeSpike": null,
          "accel6h": 0.068,
          "accel1h": 0.2556,
          "pxMom6h": -7.152,
          "fastScore": -0.1017,
          "midScore": 0.6116,
          "slowScore": -0.976,
          "compositeScore": -0.0269,
          "flowType": null,
          "persistence": {
            "label": "无显著流向",
            "hours": 0,
            "momentum": "flat",
            "breadth": 0,
            "slowFollow": false,
            "dataQuality": "partial"
          }
        },
        {
          "chain": "robinhood",
          "label": "Robinhood",
          "shareNow": 0.084,
          "shareDeltaPp": null,
          "direction": "inflow",
          "strength": 69,
          "inflection": null,
          "dataQuality": "partial",
          "dexVolChange1dPct": 69.04,
          "dexVol24hUsd": 32195759,
          "dexVolChange7dPct": 1000,
          "dexVolChange7dRawPct": 214638293.33,
          "dexVolChange7dUntrusted": true,
          "dexVolChange7dNote": "新链·基数低",
          "feesMomentum": null,
          "feeSpike": null,
          "accel6h": null,
          "accel1h": null,
          "pxMom6h": null,
          "fastScore": null,
          "midScore": 0.6904,
          "slowScore": null,
          "compositeScore": 0.6904,
          "flowType": "trading",
          "persistence": {
            "label": "积累中",
            "hours": 3,
            "momentum": "flat",
            "breadth": 2,
            "slowFollow": false,
            "dataQuality": "partial"
          }
        }
      ],
      "rotationEdges": [],
      "drivers": [
        "多链无显著资金轮动"
      ],
      "dataQuality": "partial"
    },
    "narrative": {
      "layer": "narrative",
      "eps7dPct": 2,
      "direction": "flat",
      "strength": 100,
      "confidence": "high",
      "components": [
        {
          "sector": "CEX",
          "tvl": 238497083643,
          "change7dPct": 2.61,
          "change1dPct": -1.73,
          "direction": "rotate_in",
          "strength": 25,
          "protocolCount": 77,
          "topProtocols": [
            {
              "name": "Binance CEX",
              "tvl": 134699317316,
              "change7dPct": 3.23,
              "change1dPct": -1.31
            },
            {
              "name": "OKX",
              "tvl": 21676187328,
              "change7dPct": 1.76,
              "change1dPct": -1.71
            },
            {
              "name": "Bitfinex",
              "tvl": 16168325555,
              "change7dPct": -0.23,
              "change1dPct": -2.02
            }
          ],
          "dataQuality": "ok"
        },
        {
          "sector": "Bridge",
          "tvl": 45074256141,
          "change7dPct": 3.65,
          "change1dPct": -1.53,
          "direction": "rotate_in",
          "strength": 37.5,
          "protocolCount": 145,
          "topProtocols": [
            {
              "name": "LayerZero V2",
              "tvl": 7315350075,
              "change7dPct": -0.17,
              "change1dPct": -0.87
            },
            {
              "name": "WBTC",
              "tvl": 7049847852,
              "change7dPct": 5.37,
              "change1dPct": -1.99
            },
            {
              "name": "Coinbase Bridge",
              "tvl": 5650652327,
              "change7dPct": 6.22,
              "change1dPct": -2.52
            }
          ],
          "dataQuality": "ok"
        },
        {
          "sector": "Lending",
          "tvl": 37671417260,
          "change7dPct": 4.06,
          "change1dPct": -2.2,
          "direction": "rotate_in",
          "strength": 50,
          "protocolCount": 563,
          "topProtocols": [
            {
              "name": "Aave V3",
              "tvl": 12433064612,
              "change7dPct": 4.07,
              "change1dPct": -1.67
            },
            {
              "name": "Morpho Blue",
              "tvl": 6972189867,
              "change7dPct": 6.92,
              "change1dPct": -2.03
            },
            {
              "name": "SparkLend",
              "tvl": 3517127418,
              "change7dPct": 2.88,
              "change1dPct": -3.74
            }
          ],
          "dataQuality": "ok"
        },
        {
          "sector": "Liquid Staking",
          "tvl": 33071115160,
          "change7dPct": 8.13,
          "change1dPct": -2.97,
          "direction": "rotate_in",
          "strength": 62.5,
          "protocolCount": 252,
          "topProtocols": [
            {
              "name": "Lido",
              "tvl": 15841189557,
              "change7dPct": 10.32,
              "change1dPct": -2.12
            },
            {
              "name": "Binance staked ETH",
              "tvl": 6431117090,
              "change7dPct": 10.44,
              "change1dPct": -3.1
            },
            {
              "name": "Sanctum Validator LSTs",
              "tvl": 1116270246,
              "change7dPct": 4.85,
              "change1dPct": -2.52
            }
          ],
          "dataQuality": "ok"
        },
        {
          "sector": "RWA",
          "tvl": 24167113607,
          "change7dPct": 0.17,
          "change1dPct": -0.92,
          "direction": "flat",
          "strength": 12.5,
          "protocolCount": 120,
          "topProtocols": [
            {
              "name": "Circle USYC",
              "tvl": 3107809441,
              "change7dPct": 0.01,
              "change1dPct": 0.01
            },
            {
              "name": "BlackRock BUIDL",
              "tvl": 3053924336,
              "change7dPct": -0.01,
              "change1dPct": 0.01
            },
            {
              "name": "Tether Gold",
              "tvl": 2871389046,
              "change7dPct": -1.07,
              "change1dPct": -2.56
            }
          ],
          "dataQuality": "ok"
        },
        {
          "sector": "Dexs",
          "tvl": 11495115016,
          "change7dPct": 109655617.48,
          "change1dPct": 45.34,
          "direction": "rotate_in",
          "strength": 100,
          "protocolCount": 1749,
          "topProtocols": [
            {
              "name": "PancakeSwap AMM",
              "tvl": 1655070433,
              "change7dPct": 0.44,
              "change1dPct": -1.47
            },
            {
              "name": "Uniswap V3",
              "tvl": 1435422467,
              "change7dPct": 3.87,
              "change1dPct": -0.55
            },
            {
              "name": "Curve DEX",
              "tvl": 1248392457,
              "change7dPct": 2.76,
              "change1dPct": -0.14
            }
          ],
          "dataQuality": "ok"
        },
        {
          "sector": "Staking Pool",
          "tvl": 9630235487,
          "change7dPct": 9.39,
          "change1dPct": -1.96,
          "direction": "rotate_in",
          "strength": 87.5,
          "protocolCount": 35,
          "topProtocols": [
            {
              "name": "SSV Network",
              "tvl": 8529006091,
              "change7dPct": 10.42,
              "change1dPct": -1.78
            },
            {
              "name": "Obol",
              "tvl": 553964823,
              "change7dPct": -1.77,
              "change1dPct": -3.82
            },
            {
              "name": "Marinade Native",
              "tvl": 212155772,
              "change7dPct": 8.13,
              "change1dPct": -3.74
            }
          ],
          "dataQuality": "ok"
        },
        {
          "sector": "CDP",
          "tvl": 8293820270,
          "change7dPct": 9.3,
          "change1dPct": -1.03,
          "direction": "rotate_in",
          "strength": 75,
          "protocolCount": 194,
          "topProtocols": [
            {
              "name": "Sky Lending",
              "tvl": 5886424896,
              "change7dPct": 12.73,
              "change1dPct": -0.15
            },
            {
              "name": "USDD",
              "tvl": 1290146551,
              "change7dPct": -0.75,
              "change1dPct": -3.66
            },
            {
              "name": "Lista CDP",
              "tvl": 306084929,
              "change7dPct": 3.44,
              "change1dPct": -2.8
            }
          ],
          "dataQuality": "ok"
        }
      ],
      "rotationEdges": [],
      "drivers": [
        "Dexs 板块资金轮入"
      ],
      "mindshare": {
        "trendingCoins": [
          {
            "symbol": "CASHCAT",
            "name": "Cash Cat",
            "marketCapRank": 221,
            "change24hPct": 74243643
          },
          {
            "symbol": "LAB",
            "name": "LAB",
            "marketCapRank": 126,
            "change24hPct": -84
          },
          {
            "symbol": "BTC",
            "name": "Bitcoin",
            "marketCapRank": 1,
            "change24hPct": -3
          },
          {
            "symbol": "ANSEM",
            "name": "The Black Bull",
            "marketCapRank": 244,
            "change24hPct": -28
          },
          {
            "symbol": "GRASS",
            "name": "Grass",
            "marketCapRank": 147,
            "change24hPct": -24
          },
          {
            "symbol": "SOL",
            "name": "Solana",
            "marketCapRank": 7,
            "change24hPct": -6
          },
          {
            "symbol": "PENGU",
            "name": "Pudgy Penguins",
            "marketCapRank": 114,
            "change24hPct": -9
          },
          {
            "symbol": "LIT",
            "name": "Lighter",
            "marketCapRank": 94,
            "change24hPct": -8
          },
          {
            "symbol": "ETH",
            "name": "Ethereum",
            "marketCapRank": 2,
            "change24hPct": -4
          },
          {
            "symbol": "ONDO",
            "name": "Ondo",
            "marketCapRank": 49,
            "change24hPct": -7
          }
        ],
        "trendingCategories": [
          {
            "name": "Restaking"
          },
          {
            "name": "CoinList Launchpad"
          },
          {
            "name": "Decentralized Exchange (DEX)"
          },
          {
            "name": "Index Coop Defi Index"
          },
          {
            "name": "Proof of Work (PoW)"
          },
          {
            "name": "Neobank"
          }
        ],
        "source": "coingecko-trending",
        "note": "热门搜索/注意力代理,可被刷量操纵,不代表真实资金流"
      },
      "dataQuality": "ok"
    },
    "dexCex": {
      "layer": "dexCex",
      "direction": "to_perp",
      "strength": 6,
      "confidence": "high",
      "crowding": "normal",
      "perpSpotRatio": 13.65,
      "components": [
        {
          "symbol": "BTC",
          "funding": 0.0000918252829163,
          "perpSpot": 12.3
        },
        {
          "symbol": "ETH",
          "funding": 0.0000931340392819,
          "perpSpot": 14.91
        },
        {
          "symbol": "SOL",
          "funding": 0.0000811033117328,
          "perpSpot": 14.85
        },
        {
          "symbol": "BNB",
          "funding": -0.0000223321714341,
          "perpSpot": 7.12
        }
      ],
      "rotationEdges": [],
      "drivers": [
        "资金偏合约"
      ],
      "dataQuality": "ok"
    }
  },
  "flowState": {
    "regime": "neutral",
    "moneyLocation": "偏 CEX 合约(投机/杠杆主导)",
    "rotationEdges": [],
    "agreement": {
      "bullish": 1,
      "bearish": 1,
      "net": "mixed"
    },
    "confidence": "high"
  },
  "guidance": [
    {
      "target": "CUPSEY",
      "type": "onchain_spot",
      "conviction": 33,
      "tier": "probe",
      "tierLabel": "试探",
      "tailwindLayers": [
        {
          "layer": "chain",
          "reason": "SOL 链上资金净流入",
          "pts": 0.013
        },
        {
          "layer": "链活动热度",
          "reason": "SOL 协议收入动量升温",
          "pts": 0.011
        },
        {
          "layer": "launchpad",
          "reason": "pump.fun 发射台资金升温",
          "pts": 0.018
        }
      ],
      "headwindLayers": [
        {
          "layer": "dexCex",
          "reason": "资金偏向 CEX 合约,现货承接弱",
          "pts": 0.012
        }
      ],
      "riskFlags": [],
      "rationale": "仓位档:试探 · 顺风:chain/链活动热度/launchpad · 逆风:dexCex",
      "chainTag": "solana",
      "metrics": {
        "priceUsd": 0.011749239799016048,
        "px5mPct": 1.068,
        "px1hPct": 19.579,
        "px6hPct": 58.793,
        "px24hPct": 281.075,
        "vol6hUsd": 3162979.67046204,
        "vol24hUsd": 21832398.6389129,
        "liqUsd": 342813.4723,
        "buys24h": 68630,
        "sells24h": 59066,
        "fdvUsd": 11644172.8775452,
        "marketCapUsd": 11639260.8675671,
        "ca": "6NwarBvDkXhByqVp2Qkq5i9XbtA2B3Bwe8SWGu9vpump",
        "source": "geckoterminal",
        "at": "2026-07-08T16:48:35.856Z"
      },
      "factors": [
        {
          "key": "layers",
          "label": "五层信号",
          "score": 1.8,
          "pts": 1.8,
          "detail": "层信号 rawT=0.042、rawH=0.012，宏观系数 1，按 60% 计入。"
        },
        {
          "key": "momentum",
          "label": "标的动量",
          "score": 1,
          "pts": 20,
          "detail": "标的动量按可用周期重归一计算，px24hPct=+281.08%、px6hPct=+58.79%、px1hPct=+19.58%，合成 +162.09%。"
        },
        {
          "key": "flow",
          "label": "买卖失衡",
          "score": 0.15,
          "pts": 1.5,
          "detail": "24h 买卖笔数 68630/59066，失衡度 +0.075。"
        },
        {
          "key": "turnover",
          "label": "成交/流动性",
          "score": 1,
          "pts": 10,
          "detail": "24h 成交额 21832399 美元、流动性 342813 美元，换手 63.69x。"
        }
      ],
      "dataQuality": "ok"
    },
    {
      "target": "ANSEM",
      "type": "onchain_spot",
      "conviction": 1,
      "tier": "flat",
      "tierLabel": "空仓",
      "tailwindLayers": [
        {
          "layer": "chain",
          "reason": "SOL 链上资金净流入",
          "pts": 0.013
        },
        {
          "layer": "链活动热度",
          "reason": "SOL 协议收入动量升温",
          "pts": 0.011
        }
      ],
      "headwindLayers": [
        {
          "layer": "dexCex",
          "reason": "资金偏向 CEX 合约,现货承接弱",
          "pts": 0.012
        }
      ],
      "riskFlags": [],
      "rationale": "仓位档:空仓 · 顺风:chain/链活动热度 · 逆风:dexCex",
      "chainTag": "solana",
      "metrics": {
        "priceUsd": 0.2719184053031259,
        "px5mPct": -0.329,
        "px1hPct": -1.925,
        "px6hPct": -4.019,
        "px24hPct": -27.331,
        "vol6hUsd": 7033336.98318151,
        "vol24hUsd": 38111892.9422454,
        "liqUsd": 2428284.1041,
        "buys24h": 27541,
        "sells24h": 20720,
        "fdvUsd": 271301926.864967,
        "marketCapUsd": 112776159.883162,
        "ca": "9cRCn9rGT8V2imeM2BaKs13yhMEais3ruM3rPvTGpump",
        "source": "geckoterminal",
        "at": "2026-07-08T16:48:35.856Z"
      },
      "factors": [
        {
          "key": "layers",
          "label": "五层信号",
          "score": 0.7,
          "pts": 0.7,
          "detail": "层信号 rawT=0.024、rawH=0.012，宏观系数 1，按 60% 计入。"
        },
        {
          "key": "momentum",
          "label": "标的动量",
          "score": -0.643,
          "pts": -12.9,
          "detail": "标的动量按可用周期重归一计算，px24hPct=-27.33%、px6hPct=-4.02%、px1hPct=-1.92%，合成 -15.26%。"
        },
        {
          "key": "flow",
          "label": "买卖失衡",
          "score": 0.283,
          "pts": 2.8,
          "detail": "24h 买卖笔数 27541/20720，失衡度 +0.141。"
        },
        {
          "key": "turnover",
          "label": "成交/流动性",
          "score": 1,
          "pts": 10,
          "detail": "24h 成交额 38111893 美元、流动性 2428284 美元，换手 15.69x。"
        }
      ],
      "dataQuality": "ok"
    },
    {
      "target": "MANLET",
      "type": "onchain_spot",
      "conviction": 0,
      "tier": "flat",
      "tierLabel": "空仓",
      "tailwindLayers": [
        {
          "layer": "chain",
          "reason": "SOL 链上资金净流入",
          "pts": 0.013
        },
        {
          "layer": "链活动热度",
          "reason": "SOL 协议收入动量升温",
          "pts": 0.011
        },
        {
          "layer": "launchpad",
          "reason": "pump.fun 发射台资金升温",
          "pts": 0.018
        }
      ],
      "headwindLayers": [
        {
          "layer": "dexCex",
          "reason": "资金偏向 CEX 合约,现货承接弱",
          "pts": 0.012
        }
      ],
      "riskFlags": [
        "流动性薄(<$30万)，出场滑点风险"
      ],
      "rationale": "仓位档:空仓 · 顺风:chain/链活动热度/launchpad · 逆风:dexCex · 风险:1 项",
      "chainTag": "solana",
      "metrics": {
        "priceUsd": 0.0029306576474130482,
        "px5mPct": 0.015,
        "px1hPct": -13.361,
        "px6hPct": -4.875,
        "px24hPct": -57.252,
        "vol6hUsd": 465675.150895468,
        "vol24hUsd": 3126179.8883088,
        "liqUsd": 192396.6616,
        "buys24h": 12557,
        "sells24h": 10803,
        "fdvUsd": 2891844.54068037,
        "marketCapUsd": 2891845.11432291,
        "ca": "DdPrHYqM8Ueovnk9kAnAgoGhswkuaTqmxcoZzU3Zpump",
        "source": "geckoterminal",
        "at": "2026-07-08T16:48:35.856Z"
      },
      "factors": [
        {
          "key": "layers",
          "label": "五层信号",
          "score": 1.8,
          "pts": 1.8,
          "detail": "层信号 rawT=0.042、rawH=0.012，宏观系数 1，按 60% 计入。"
        },
        {
          "key": "momentum",
          "label": "标的动量",
          "score": -0.927,
          "pts": -18.5,
          "detail": "标的动量按可用周期重归一计算，px24hPct=-57.25%、px6hPct=-4.87%、px1hPct=-13.36%，合成 -32.76%。"
        },
        {
          "key": "flow",
          "label": "买卖失衡",
          "score": 0.15,
          "pts": 1.5,
          "detail": "24h 买卖笔数 12557/10803，失衡度 +0.075。"
        },
        {
          "key": "turnover",
          "label": "成交/流动性",
          "score": 1,
          "pts": 10,
          "detail": "24h 成交额 3126180 美元、流动性 192397 美元，换手 16.25x。"
        }
      ],
      "dataQuality": "ok"
    },
    {
      "target": "AERO",
      "type": "onchain_spot",
      "conviction": 0,
      "tier": "flat",
      "tierLabel": "空仓",
      "tailwindLayers": [
        {
          "layer": "chain",
          "reason": "Base 链上资金净流入",
          "pts": 0.032
        },
        {
          "layer": "链活动热度",
          "reason": "Base 协议收入动量升温",
          "pts": 0.012
        }
      ],
      "headwindLayers": [
        {
          "layer": "dexCex",
          "reason": "资金偏向 CEX 合约,现货承接弱",
          "pts": 0.012
        }
      ],
      "riskFlags": [],
      "rationale": "仓位档:空仓 · 顺风:chain/链活动热度 · 逆风:dexCex",
      "chainTag": "base",
      "metrics": {
        "priceUsd": 0.523881742238297,
        "px5mPct": 0,
        "px1hPct": 0.772,
        "px6hPct": -0.341,
        "px24hPct": -12.395,
        "vol6hUsd": 1681909.64075336,
        "vol24hUsd": 4958830.53761809,
        "liqUsd": 33284530.7846,
        "buys24h": 1191,
        "sells24h": 4110,
        "fdvUsd": 1011644306.84383,
        "marketCapUsd": 504907110.828635,
        "ca": "0x940181a94a35a4569e4529a3cdfb74e38fd98631",
        "source": "geckoterminal",
        "at": "2026-07-08T16:48:35.856Z"
      },
      "factors": [
        {
          "key": "layers",
          "label": "五层信号",
          "score": 1.9,
          "pts": 1.9,
          "detail": "层信号 rawT=0.044、rawH=0.012，宏观系数 1，按 60% 计入。"
        },
        {
          "key": "momentum",
          "label": "标的动量",
          "score": -0.298,
          "pts": -6,
          "detail": "标的动量按可用周期重归一计算，px24hPct=-12.39%、px6hPct=-0.34%、px1hPct=+0.77%，合成 -6.15%。"
        },
        {
          "key": "flow",
          "label": "买卖失衡",
          "score": -1,
          "pts": -10,
          "detail": "24h 买卖笔数 1191/4110，失衡度 -0.551。"
        },
        {
          "key": "turnover",
          "label": "成交/流动性",
          "score": 0,
          "pts": 0,
          "detail": "24h 成交额 4958831 美元、流动性 33284531 美元，换手 0.15x。"
        }
      ],
      "dataQuality": "ok"
    },
    {
      "target": "VELVET",
      "type": "onchain_spot",
      "conviction": 5,
      "tier": "flat",
      "tierLabel": "空仓",
      "tailwindLayers": [
        {
          "layer": "chain",
          "reason": "Base 链上资金净流入",
          "pts": 0.032
        },
        {
          "layer": "链活动热度",
          "reason": "Base 协议收入动量升温",
          "pts": 0.012
        }
      ],
      "headwindLayers": [
        {
          "layer": "dexCex",
          "reason": "资金偏向 CEX 合约,现货承接弱",
          "pts": 0.012
        }
      ],
      "riskFlags": [],
      "rationale": "仓位档:空仓 · 顺风:chain/链活动热度 · 逆风:dexCex",
      "chainTag": "base",
      "metrics": {
        "priceUsd": 0.414138793849822,
        "px5mPct": -0.43,
        "px1hPct": 2.611,
        "px6hPct": 0.273,
        "px24hPct": 4.95,
        "vol6hUsd": 594505.392640799,
        "vol24hUsd": 3012539.75698111,
        "liqUsd": 3041676.0566,
        "buys24h": 22502,
        "sells24h": 21982,
        "fdvUsd": 3269523.22374251,
        "marketCapUsd": 174188121.237763,
        "ca": "0xbf927b841994731c573bdf09ceb0c6b0aa887cdd",
        "source": "geckoterminal",
        "at": "2026-07-08T16:48:35.856Z"
      },
      "factors": [
        {
          "key": "layers",
          "label": "五层信号",
          "score": 1.9,
          "pts": 1.9,
          "detail": "层信号 rawT=0.044、rawH=0.012，宏观系数 1，按 60% 计入。"
        },
        {
          "key": "momentum",
          "label": "标的动量",
          "score": 0.153,
          "pts": 3.1,
          "detail": "标的动量按可用周期重归一计算，px24hPct=+4.95%、px6hPct=+0.27%、px1hPct=+2.61%，合成 +3.08%。"
        },
        {
          "key": "flow",
          "label": "买卖失衡",
          "score": 0.023,
          "pts": 0.2,
          "detail": "24h 买卖笔数 22502/21982，失衡度 +0.012。"
        },
        {
          "key": "turnover",
          "label": "成交/流动性",
          "score": 0,
          "pts": 0,
          "detail": "24h 成交额 3012540 美元、流动性 3041676 美元，换手 0.99x。"
        }
      ],
      "dataQuality": "ok"
    },
    {
      "target": "POD",
      "type": "onchain_spot",
      "conviction": 0,
      "tier": "flat",
      "tierLabel": "空仓",
      "tailwindLayers": [
        {
          "layer": "chain",
          "reason": "Base 链上资金净流入",
          "pts": 0.032
        },
        {
          "layer": "链活动热度",
          "reason": "Base 协议收入动量升温",
          "pts": 0.012
        }
      ],
      "headwindLayers": [
        {
          "layer": "dexCex",
          "reason": "资金偏向 CEX 合约,现货承接弱",
          "pts": 0.012
        }
      ],
      "riskFlags": [],
      "rationale": "仓位档:空仓 · 顺风:chain/链活动热度 · 逆风:dexCex",
      "chainTag": "base",
      "metrics": {
        "priceUsd": 0.423429579521096,
        "px5mPct": -1.549,
        "px1hPct": 1.143,
        "px6hPct": -2.913,
        "px24hPct": -15.163,
        "vol6hUsd": 207910.438689699,
        "vol24hUsd": 979351.989743839,
        "liqUsd": 4769309.062,
        "buys24h": 329,
        "sells24h": 279,
        "fdvUsd": 211714789.74512,
        "marketCapUsd": 18446648.2876861,
        "ca": "0xed664536023d8e4b1640c394777d34abaff1df8f",
        "source": "geckoterminal",
        "at": "2026-07-08T16:48:35.856Z"
      },
      "factors": [
        {
          "key": "layers",
          "label": "五层信号",
          "score": 1.9,
          "pts": 1.9,
          "detail": "层信号 rawT=0.044、rawH=0.012，宏观系数 1，按 60% 计入。"
        },
        {
          "key": "momentum",
          "label": "标的动量",
          "score": -0.39,
          "pts": -7.8,
          "detail": "标的动量按可用周期重归一计算，px24hPct=-15.16%、px6hPct=-2.91%、px1hPct=+1.14%，合成 -8.23%。"
        },
        {
          "key": "flow",
          "label": "买卖失衡",
          "score": 0.164,
          "pts": 1.6,
          "detail": "24h 买卖笔数 329/279，失衡度 +0.082。"
        },
        {
          "key": "turnover",
          "label": "成交/流动性",
          "score": 0,
          "pts": 0,
          "detail": "24h 成交额 979352 美元、流动性 4769309 美元，换手 0.21x。"
        }
      ],
      "dataQuality": "ok"
    },
    {
      "target": "ASTEROID",
      "type": "onchain_spot",
      "conviction": 4,
      "tier": "flat",
      "tierLabel": "空仓",
      "tailwindLayers": [
        {
          "layer": "chain",
          "reason": "ETH 主网 链上资金净流入",
          "pts": 0.061
        },
        {
          "layer": "链活动热度",
          "reason": "ETH 主网 协议收入动量升温",
          "pts": 0.05
        }
      ],
      "headwindLayers": [
        {
          "layer": "dexCex",
          "reason": "资金偏向 CEX 合约,现货承接弱",
          "pts": 0.012
        }
      ],
      "riskFlags": [],
      "rationale": "仓位档:空仓 · 顺风:chain/链活动热度 · 逆风:dexCex",
      "chainTag": "ethereum",
      "metrics": {
        "priceUsd": 0.0000574771916930544,
        "px5mPct": 0.437,
        "px1hPct": -1.065,
        "px6hPct": 6.048,
        "px24hPct": -20.238,
        "vol6hUsd": 613656.333313262,
        "vol24hUsd": 3409224.21168327,
        "liqUsd": 1603967.8698,
        "buys24h": 1935,
        "sells24h": 1428,
        "fdvUsd": 24179425.7741767,
        "marketCapUsd": 24180079.7720661,
        "ca": "0xf280b16ef293d8e534e370794ef26bf312694126",
        "source": "geckoterminal",
        "at": "2026-07-08T16:48:35.856Z"
      },
      "factors": [
        {
          "key": "layers",
          "label": "五层信号",
          "score": 6,
          "pts": 6,
          "detail": "层信号 rawT=0.111、rawH=0.012，宏观系数 1，按 60% 计入。"
        },
        {
          "key": "momentum",
          "label": "标的动量",
          "score": -0.402,
          "pts": -8,
          "detail": "标的动量按可用周期重归一计算，px24hPct=-20.24%、px6hPct=+6.05%、px1hPct=-1.06%，合成 -8.52%。"
        },
        {
          "key": "flow",
          "label": "买卖失衡",
          "score": 0.302,
          "pts": 3,
          "detail": "24h 买卖笔数 1935/1428，失衡度 +0.151。"
        },
        {
          "key": "turnover",
          "label": "成交/流动性",
          "score": 0.327,
          "pts": 3.3,
          "detail": "24h 成交额 3409224 美元、流动性 1603968 美元，换手 2.13x。"
        }
      ],
      "dataQuality": "ok"
    },
    {
      "target": "LDO",
      "type": "onchain_spot",
      "conviction": 23,
      "tier": "flat",
      "tierLabel": "空仓",
      "tailwindLayers": [
        {
          "layer": "chain",
          "reason": "ETH 主网 链上资金净流入",
          "pts": 0.061
        },
        {
          "layer": "链活动热度",
          "reason": "ETH 主网 协议收入动量升温",
          "pts": 0.05
        }
      ],
      "headwindLayers": [
        {
          "layer": "dexCex",
          "reason": "资金偏向 CEX 合约,现货承接弱",
          "pts": 0.012
        }
      ],
      "riskFlags": [],
      "rationale": "仓位档:空仓 · 顺风:chain/链活动热度 · 逆风:dexCex",
      "chainTag": "ethereum",
      "metrics": {
        "priceUsd": 0.337505436616661,
        "px5mPct": -0.173,
        "px1hPct": 4.782,
        "px6hPct": 7.662,
        "px24hPct": 9.554,
        "vol6hUsd": 796118.436093447,
        "vol24hUsd": 5322985.32471546,
        "liqUsd": 489800.3873,
        "buys24h": 1408,
        "sells24h": 1478,
        "fdvUsd": 337505434.828225,
        "marketCapUsd": 284461274.321251,
        "ca": "0x5a98fcbea516cf06857215779fd812ca3bef1b32",
        "source": "geckoterminal",
        "at": "2026-07-08T16:48:35.856Z"
      },
      "factors": [
        {
          "key": "layers",
          "label": "五层信号",
          "score": 6,
          "pts": 6,
          "detail": "层信号 rawT=0.111、rawH=0.012，宏观系数 1，按 60% 计入。"
        },
        {
          "key": "momentum",
          "label": "标的动量",
          "score": 0.381,
          "pts": 7.6,
          "detail": "标的动量按可用周期重归一计算，px24hPct=+9.55%、px6hPct=+7.66%、px1hPct=+4.78%，合成 +8.03%。"
        },
        {
          "key": "flow",
          "label": "买卖失衡",
          "score": -0.049,
          "pts": -0.5,
          "detail": "24h 买卖笔数 1408/1478，失衡度 -0.024。"
        },
        {
          "key": "turnover",
          "label": "成交/流动性",
          "score": 1,
          "pts": 10,
          "detail": "24h 成交额 5322985 美元、流动性 489800 美元，换手 10.87x。"
        }
      ],
      "dataQuality": "ok"
    },
    {
      "target": "UNI",
      "type": "onchain_spot",
      "conviction": 9,
      "tier": "flat",
      "tierLabel": "空仓",
      "tailwindLayers": [
        {
          "layer": "chain",
          "reason": "ETH 主网 链上资金净流入",
          "pts": 0.061
        },
        {
          "layer": "链活动热度",
          "reason": "ETH 主网 协议收入动量升温",
          "pts": 0.05
        }
      ],
      "headwindLayers": [
        {
          "layer": "dexCex",
          "reason": "资金偏向 CEX 合约,现货承接弱",
          "pts": 0.012
        }
      ],
      "riskFlags": [],
      "rationale": "仓位档:空仓 · 顺风:chain/链活动热度 · 逆风:dexCex",
      "chainTag": "ethereum",
      "metrics": {
        "priceUsd": 3.30031301111435,
        "px5mPct": 0.209,
        "px1hPct": 0.925,
        "px6hPct": 0.552,
        "px24hPct": 1.278,
        "vol6hUsd": 1608890.6218362,
        "vol24hUsd": 6031523.28405616,
        "liqUsd": 13391394.5498,
        "buys24h": 464,
        "sells24h": 388,
        "fdvUsd": 2947649549.60008,
        "marketCapUsd": 2049532536.63979,
        "ca": "0x1f9840a85d5af5bf1d1762f925bdaddc4201f984",
        "source": "geckoterminal",
        "at": "2026-07-08T16:48:35.856Z"
      },
      "factors": [
        {
          "key": "layers",
          "label": "五层信号",
          "score": 6,
          "pts": 6,
          "detail": "层信号 rawT=0.111、rawH=0.012，宏观系数 1，按 60% 计入。"
        },
        {
          "key": "momentum",
          "label": "标的动量",
          "score": 0.049,
          "pts": 1,
          "detail": "标的动量按可用周期重归一计算，px24hPct=+1.28%、px6hPct=+0.55%、px1hPct=+0.93%，合成 +0.99%。"
        },
        {
          "key": "flow",
          "label": "买卖失衡",
          "score": 0.178,
          "pts": 1.8,
          "detail": "24h 买卖笔数 464/388，失衡度 +0.089。"
        },
        {
          "key": "turnover",
          "label": "成交/流动性",
          "score": 0,
          "pts": 0,
          "detail": "24h 成交额 6031523 美元、流动性 13391395 美元，换手 0.45x。"
        }
      ],
      "dataQuality": "ok"
    },
    {
      "target": "LAB",
      "type": "onchain_spot",
      "conviction": 0,
      "tier": "flat",
      "tierLabel": "空仓",
      "tailwindLayers": [
        {
          "layer": "链活动热度",
          "reason": "BSC 协议收入动量升温",
          "pts": 0.017
        }
      ],
      "headwindLayers": [
        {
          "layer": "dexCex",
          "reason": "资金偏向 CEX 合约,现货承接弱",
          "pts": 0.012
        }
      ],
      "riskFlags": [
        "流动性薄(<$30万)，出场滑点风险"
      ],
      "rationale": "仓位档:空仓 · 顺风:链活动热度 · 逆风:dexCex · 风险:1 项",
      "chainTag": "bsc",
      "metrics": {
        "priceUsd": 1.2399963787504,
        "px5mPct": 6.215,
        "px1hPct": 6.219,
        "px6hPct": -44.242,
        "px24hPct": -81.573,
        "vol6hUsd": 4715536.27737246,
        "vol24hUsd": 24850727.3769565,
        "liqUsd": 159921.8174,
        "buys24h": 83160,
        "sells24h": 79444,
        "fdvUsd": 1236873299.69416,
        "marketCapUsd": 386575901.229649,
        "ca": "0x7ec43cf65f1663f820427c62a5780b8f2e25593a",
        "source": "geckoterminal",
        "at": "2026-07-08T16:48:35.856Z"
      },
      "factors": [
        {
          "key": "layers",
          "label": "五层信号",
          "score": 0.3,
          "pts": 0.3,
          "detail": "层信号 rawT=0.017、rawH=0.012，宏观系数 1，按 60% 计入。"
        },
        {
          "key": "momentum",
          "label": "标的动量",
          "score": -0.99,
          "pts": -19.8,
          "detail": "标的动量按可用周期重归一计算，px24hPct=-81.57%、px6hPct=-44.24%、px1hPct=+6.22%，合成 -52.82%。"
        },
        {
          "key": "flow",
          "label": "买卖失衡",
          "score": 0.046,
          "pts": 0.5,
          "detail": "24h 买卖笔数 83160/79444，失衡度 +0.023。"
        },
        {
          "key": "turnover",
          "label": "成交/流动性",
          "score": 1,
          "pts": 10,
          "detail": "24h 成交额 24850727 美元、流动性 159922 美元，换手 155.39x。"
        }
      ],
      "dataQuality": "ok"
    },
    {
      "target": "EVAA",
      "type": "onchain_spot",
      "conviction": 10,
      "tier": "flat",
      "tierLabel": "空仓",
      "tailwindLayers": [
        {
          "layer": "链活动热度",
          "reason": "BSC 协议收入动量升温",
          "pts": 0.017
        }
      ],
      "headwindLayers": [
        {
          "layer": "dexCex",
          "reason": "资金偏向 CEX 合约,现货承接弱",
          "pts": 0.012
        }
      ],
      "riskFlags": [],
      "rationale": "仓位档:空仓 · 顺风:链活动热度 · 逆风:dexCex",
      "chainTag": "bsc",
      "metrics": {
        "priceUsd": 2.61430850554608,
        "px5mPct": -1.945,
        "px1hPct": -9.455,
        "px6hPct": -20.505,
        "px24hPct": 16.073,
        "vol6hUsd": 3233948.33406503,
        "vol24hUsd": 15553407.1067546,
        "liqUsd": 349173.5121,
        "buys24h": 120402,
        "sells24h": 129528,
        "fdvUsd": 78109786.8865501,
        "marketCapUsd": 17230946.0848044,
        "ca": "0xaa036928c9c0df07d525b55ea8ee690bb5a628c1",
        "source": "geckoterminal",
        "at": "2026-07-08T16:48:35.856Z"
      },
      "factors": [
        {
          "key": "layers",
          "label": "五层信号",
          "score": 0.3,
          "pts": 0.3,
          "detail": "层信号 rawT=0.017、rawH=0.012，宏观系数 1，按 60% 计入。"
        },
        {
          "key": "momentum",
          "label": "标的动量",
          "score": 0,
          "pts": 0,
          "detail": "标的动量按可用周期重归一计算，px24hPct=+16.07%、px6hPct=-20.5%、px1hPct=-9.45%，合成 -0.01%。"
        },
        {
          "key": "flow",
          "label": "买卖失衡",
          "score": -0.073,
          "pts": -0.7,
          "detail": "24h 买卖笔数 120402/129528，失衡度 -0.037。"
        },
        {
          "key": "turnover",
          "label": "成交/流动性",
          "score": 1,
          "pts": 10,
          "detail": "24h 成交额 15553407 美元、流动性 349174 美元，换手 44.54x。"
        }
      ],
      "dataQuality": "ok"
    },
    {
      "target": "BIBI",
      "type": "onchain_spot",
      "conviction": 0,
      "tier": "flat",
      "tierLabel": "空仓",
      "tailwindLayers": [
        {
          "layer": "链活动热度",
          "reason": "BSC 协议收入动量升温",
          "pts": 0.017
        }
      ],
      "headwindLayers": [
        {
          "layer": "dexCex",
          "reason": "资金偏向 CEX 合约,现货承接弱",
          "pts": 0.012
        }
      ],
      "riskFlags": [
        "流动性薄(<$30万)，出场滑点风险"
      ],
      "rationale": "仓位档:空仓 · 顺风:链活动热度 · 逆风:dexCex · 风险:1 项",
      "chainTag": "bsc",
      "metrics": {
        "priceUsd": 0.00763650143699426,
        "px5mPct": -2.107,
        "px1hPct": -5.837,
        "px6hPct": -24.649,
        "px24hPct": -34.485,
        "vol6hUsd": 2300248.5818351,
        "vol24hUsd": 8962703.39875358,
        "liqUsd": 297934.025,
        "buys24h": 19644,
        "sells24h": 15721,
        "fdvUsd": 7665748.009,
        "marketCapUsd": null,
        "ca": "0x0b6d8934fc8838b1027b510364a2087317bd4444",
        "source": "geckoterminal",
        "at": "2026-07-08T16:48:35.856Z"
      },
      "factors": [
        {
          "key": "layers",
          "label": "五层信号",
          "score": 0.3,
          "pts": 0.3,
          "detail": "层信号 rawT=0.017、rawH=0.012，宏观系数 1，按 60% 计入。"
        },
        {
          "key": "momentum",
          "label": "标的动量",
          "score": -0.859,
          "pts": -17.2,
          "detail": "标的动量按可用周期重归一计算，px24hPct=-34.48%、px6hPct=-24.65%、px1hPct=-5.84%，合成 -25.8%。"
        },
        {
          "key": "flow",
          "label": "买卖失衡",
          "score": 0.222,
          "pts": 2.2,
          "detail": "24h 买卖笔数 19644/15721，失衡度 +0.111。"
        },
        {
          "key": "turnover",
          "label": "成交/流动性",
          "score": 1,
          "pts": 10,
          "detail": "24h 成交额 8962703 美元、流动性 297934 美元，换手 30.08x。"
        }
      ],
      "dataQuality": "ok"
    }
  ],
  "appRevenueHeat": {
    "layer": "appRevenue",
    "dataQuality": "ok",
    "note": "协议收入=活动热度,非流动性/净流入",
    "byChain": [
      {
        "chain": "solana",
        "label": "SOL",
        "dataQuality": "ok",
        "totalRevenue24h": 3658069,
        "topApps": [
          {
            "protocol": "pump.fun",
            "revenue24h": 799202,
            "revenue7d": 5287471,
            "share": 21.8,
            "momentum": 0.058,
            "direction": "heating"
          },
          {
            "protocol": "Collector Crypt",
            "revenue24h": 426198,
            "revenue7d": 2179313,
            "share": 11.7,
            "momentum": 0.369,
            "direction": "heating"
          },
          {
            "protocol": "Axiom",
            "revenue24h": 369347,
            "revenue7d": 1838517,
            "share": 10.1,
            "momentum": 0.406,
            "direction": "heating"
          },
          {
            "protocol": "PumpSwap",
            "revenue24h": 336406,
            "revenue7d": 2281860,
            "share": 9.2,
            "momentum": 0.032,
            "direction": "flat"
          },
          {
            "protocol": "Phantom Wallet",
            "revenue24h": 324615,
            "revenue7d": 1801727,
            "share": 8.9,
            "momentum": 0.261,
            "direction": "heating"
          }
        ],
        "chainHeat": true,
        "dominantApp": {
          "protocol": "pump.fun",
          "revenue24h": 799202,
          "share": 21.8
        },
        "singleAppSpike": false
      },
      {
        "chain": "base",
        "label": "Base",
        "dataQuality": "ok",
        "totalRevenue24h": 493070,
        "topApps": [
          {
            "protocol": "Aerodrome Slipstream",
            "revenue24h": 137414,
            "revenue7d": 925587,
            "share": 27.9,
            "momentum": 0.039,
            "direction": "flat"
          },
          {
            "protocol": "Base",
            "revenue24h": 72868,
            "revenue7d": 459253,
            "share": 14.8,
            "momentum": 0.111,
            "direction": "heating"
          },
          {
            "protocol": "Uniswap V3",
            "revenue24h": 51698,
            "revenue7d": 329953,
            "share": 10.5,
            "momentum": 0.097,
            "direction": "heating"
          },
          {
            "protocol": "Aerodrome V1",
            "revenue24h": 34873,
            "revenue7d": 223742,
            "share": 7.1,
            "momentum": 0.091,
            "direction": "heating"
          },
          {
            "protocol": "Metronome Synth",
            "revenue24h": 29181,
            "revenue7d": 89075,
            "share": 5.9,
            "momentum": 1.293,
            "direction": "heating"
          }
        ],
        "chainHeat": true,
        "dominantApp": {
          "protocol": "Aerodrome Slipstream",
          "revenue24h": 137414,
          "share": 27.9
        },
        "singleAppSpike": false
      },
      {
        "chain": "ethereum",
        "label": "ETH 主网",
        "dataQuality": "ok",
        "totalRevenue24h": 1787065,
        "topApps": [
          {
            "protocol": "Sky Lending",
            "revenue24h": 445859,
            "revenue7d": 3103142,
            "share": 24.9,
            "momentum": 0.006,
            "direction": "flat"
          },
          {
            "protocol": "Convex Finance",
            "revenue24h": 198205,
            "revenue7d": 76288,
            "share": 11.1,
            "momentum": 17.187,
            "direction": "heating"
          },
          {
            "protocol": "LayerZero V2",
            "revenue24h": 136983,
            "revenue7d": 0,
            "share": 7.7,
            "momentum": null,
            "direction": "unknown"
          },
          {
            "protocol": "Spark Liquidity Layer",
            "revenue24h": 94936,
            "revenue7d": 200838,
            "share": 5.3,
            "momentum": 2.309,
            "direction": "heating"
          },
          {
            "protocol": "Aave V3",
            "revenue24h": 91697,
            "revenue7d": 656572,
            "share": 5.1,
            "momentum": -0.022,
            "direction": "flat"
          }
        ],
        "chainHeat": true,
        "dominantApp": {
          "protocol": "Sky Lending",
          "revenue24h": 445859,
          "share": 24.9
        },
        "singleAppSpike": false
      },
      {
        "chain": "bsc",
        "label": "BSC",
        "dataQuality": "ok",
        "totalRevenue24h": 733878,
        "topApps": [
          {
            "protocol": "GMGN",
            "revenue24h": 307869,
            "revenue7d": 1621375,
            "share": 42,
            "momentum": 0.329,
            "direction": "heating"
          },
          {
            "protocol": "four.meme",
            "revenue24h": 127446,
            "revenue7d": 543592,
            "share": 17.4,
            "momentum": 0.641,
            "direction": "heating"
          },
          {
            "protocol": "Binance Alpha",
            "revenue24h": 48099,
            "revenue7d": 367751,
            "share": 6.6,
            "momentum": -0.084,
            "direction": "cooling"
          },
          {
            "protocol": "BSC",
            "revenue24h": 39013,
            "revenue7d": 227366,
            "share": 5.3,
            "momentum": 0.201,
            "direction": "heating"
          },
          {
            "protocol": "Predict Fun",
            "revenue24h": 37836,
            "revenue7d": 229206,
            "share": 5.2,
            "momentum": 0.156,
            "direction": "heating"
          }
        ],
        "chainHeat": true,
        "dominantApp": {
          "protocol": "GMGN",
          "revenue24h": 307869,
          "share": 42
        },
        "singleAppSpike": false
      },
      {
        "chain": "robinhood",
        "label": "Robinhood",
        "dataQuality": "ok",
        "totalRevenue24h": 0,
        "topApps": [
          {
            "protocol": "Curve DEX",
            "revenue24h": 0,
            "revenue7d": 0,
            "share": 0,
            "momentum": null,
            "direction": "unknown"
          },
          {
            "protocol": "PancakeSwap AMM",
            "revenue24h": 0,
            "revenue7d": 0,
            "share": 0,
            "momentum": null,
            "direction": "unknown"
          },
          {
            "protocol": "Uniswap V2",
            "revenue24h": 0,
            "revenue7d": 0,
            "share": 0,
            "momentum": null,
            "direction": "unknown"
          },
          {
            "protocol": "Uniswap V3",
            "revenue24h": 0,
            "revenue7d": 0,
            "share": 0,
            "momentum": null,
            "direction": "unknown"
          },
          {
            "protocol": "PancakeSwap AMM V3",
            "revenue24h": 0,
            "revenue7d": 0,
            "share": 0,
            "momentum": null,
            "direction": "unknown"
          }
        ],
        "chainHeat": false,
        "dominantApp": {
          "protocol": "Curve DEX",
          "revenue24h": 0,
          "share": 0
        },
        "singleAppSpike": false
      }
    ]
  },
  "stableTide": {
    "sideChannel": "stableTide",
    "mcapUsd": 302343668227,
    "spanHours": 137.1,
    "points": 77,
    "note": "总量=钱进出 crypto 池子的变化;链间份额=池内轮动。旁路展示,不进五层引擎/conviction(v1)。",
    "direction": "outflow",
    "delta24hPct": -0.376,
    "delta7dPct": null,
    "emaGapPct": null,
    "cusumAlarm": null,
    "dataQuality": "partial"
  },
  "dataHealth": {
    "layers": [
      {
        "layer": "macro",
        "dataQuality": "ok",
        "confidence": "high"
      },
      {
        "layer": "launchpad",
        "dataQuality": "ok",
        "confidence": "high"
      },
      {
        "layer": "chain",
        "dataQuality": "partial",
        "confidence": "medium"
      },
      {
        "layer": "narrative",
        "dataQuality": "ok",
        "confidence": "high"
      },
      {
        "layer": "dexCex",
        "dataQuality": "ok",
        "confidence": "high"
      }
    ],
    "sourceStatus": [
      {
        "source": "fred-net-liquidity",
        "status": "ok"
      },
      {
        "source": "defillama-stablecoinchains",
        "status": "ok"
      },
      {
        "source": "geckoterminal-trending",
        "status": "partial",
        "message": "robinhood: unsupported GeckoTerminal chain robinhood; fallback unsupported CoinGecko category robinhood"
      },
      {
        "source": "defillama-launchpad-fees",
        "status": "ok"
      },
      {
        "source": "defillama-chain-fees",
        "status": "ok"
      },
      {
        "source": "defillama-dexs",
        "status": "ok"
      },
      {
        "source": "coingecko-trending",
        "status": "ok"
      },
      {
        "source": "defillama-categories",
        "status": "ok"
      },
      {
        "source": "okx-derivatives",
        "status": "ok"
      }
    ]
  },
  "advisory": "本面板为资金流向辅助判断,仅供观察与仓位参考,不构成下单指令;真实交易由用户手动执行。"
}
